package com.baidu.android.pushservice.util;

import android.content.Context;

final class c
  implements Runnable
{
  c(Context paramContext, String paramString1, String paramString2) {}
  
  /* Error */
  public final void run()
  {
    // Byte code:
    //   0: new 28	org/apache/http/impl/client/DefaultHttpClient
    //   3: dup
    //   4: invokespecial 29	org/apache/http/impl/client/DefaultHttpClient:<init>	()V
    //   7: astore_3
    //   8: aload_3
    //   9: invokeinterface 35 1 0
    //   14: ldc 37
    //   16: sipush 10000
    //   19: invokestatic 43	java/lang/Integer:valueOf	(I)Ljava/lang/Integer;
    //   22: invokeinterface 49 3 0
    //   27: pop
    //   28: aload_3
    //   29: invokeinterface 35 1 0
    //   34: ldc 51
    //   36: sipush 10000
    //   39: invokestatic 43	java/lang/Integer:valueOf	(I)Ljava/lang/Integer;
    //   42: invokeinterface 49 3 0
    //   47: pop
    //   48: aload_0
    //   49: getfield 15	com/baidu/android/pushservice/util/c:a	Landroid/content/Context;
    //   52: aload_0
    //   53: getfield 17	com/baidu/android/pushservice/util/c:b	Ljava/lang/String;
    //   56: aload_0
    //   57: getfield 19	com/baidu/android/pushservice/util/c:c	Ljava/lang/String;
    //   60: invokestatic 56	com/baidu/android/pushservice/util/a:b	(Landroid/content/Context;Ljava/lang/String;Ljava/lang/String;)Ljava/lang/String;
    //   63: astore_2
    //   64: new 58	java/net/URL
    //   67: dup
    //   68: aload_2
    //   69: invokespecial 61	java/net/URL:<init>	(Ljava/lang/String;)V
    //   72: astore_2
    //   73: new 63	java/net/URI
    //   76: dup
    //   77: aload_2
    //   78: invokevirtual 67	java/net/URL:getProtocol	()Ljava/lang/String;
    //   81: aload_2
    //   82: invokevirtual 70	java/net/URL:getHost	()Ljava/lang/String;
    //   85: aload_2
    //   86: invokevirtual 73	java/net/URL:getPath	()Ljava/lang/String;
    //   89: aload_2
    //   90: invokevirtual 76	java/net/URL:getQuery	()Ljava/lang/String;
    //   93: aconst_null
    //   94: invokespecial 79	java/net/URI:<init>	(Ljava/lang/String;Ljava/lang/String;Ljava/lang/String;Ljava/lang/String;Ljava/lang/String;)V
    //   97: astore_2
    //   98: ldc 81
    //   100: new 83	java/lang/StringBuilder
    //   103: dup
    //   104: ldc 85
    //   106: invokespecial 86	java/lang/StringBuilder:<init>	(Ljava/lang/String;)V
    //   109: aload_2
    //   110: invokevirtual 89	java/net/URI:toString	()Ljava/lang/String;
    //   113: invokevirtual 93	java/lang/StringBuilder:append	(Ljava/lang/String;)Ljava/lang/StringBuilder;
    //   116: invokevirtual 94	java/lang/StringBuilder:toString	()Ljava/lang/String;
    //   119: invokestatic 99	com/baidu/frontia/base/a/a/a:b	(Ljava/lang/String;Ljava/lang/String;)V
    //   122: new 101	org/apache/http/client/methods/HttpPost
    //   125: dup
    //   126: aload_2
    //   127: invokespecial 104	org/apache/http/client/methods/HttpPost:<init>	(Ljava/net/URI;)V
    //   130: astore_2
    //   131: aload_2
    //   132: ldc 106
    //   134: ldc 108
    //   136: invokevirtual 111	org/apache/http/client/methods/HttpPost:addHeader	(Ljava/lang/String;Ljava/lang/String;)V
    //   139: aload_2
    //   140: ldc 113
    //   142: ldc 115
    //   144: invokevirtual 111	org/apache/http/client/methods/HttpPost:addHeader	(Ljava/lang/String;Ljava/lang/String;)V
    //   147: aload_3
    //   148: aload_2
    //   149: invokeinterface 119 2 0
    //   154: astore_2
    //   155: aload_2
    //   156: invokeinterface 125 1 0
    //   161: invokestatic 130	org/apache/http/util/EntityUtils:toString	(Lorg/apache/http/HttpEntity;)Ljava/lang/String;
    //   164: astore_3
    //   165: aload_2
    //   166: invokeinterface 134 1 0
    //   171: invokeinterface 140 1 0
    //   176: sipush 200
    //   179: if_icmpne +35 -> 214
    //   182: ldc 81
    //   184: new 83	java/lang/StringBuilder
    //   187: dup
    //   188: ldc -114
    //   190: invokespecial 86	java/lang/StringBuilder:<init>	(Ljava/lang/String;)V
    //   193: aload_3
    //   194: invokevirtual 93	java/lang/StringBuilder:append	(Ljava/lang/String;)Ljava/lang/StringBuilder;
    //   197: invokevirtual 94	java/lang/StringBuilder:toString	()Ljava/lang/String;
    //   200: invokestatic 99	com/baidu/frontia/base/a/a/a:b	(Ljava/lang/String;Ljava/lang/String;)V
    //   203: return
    //   204: astore_2
    //   205: aload_2
    //   206: invokevirtual 145	java/lang/Exception:printStackTrace	()V
    //   209: aconst_null
    //   210: astore_2
    //   211: goto -113 -> 98
    //   214: ldc 81
    //   216: new 83	java/lang/StringBuilder
    //   219: dup
    //   220: ldc -109
    //   222: invokespecial 86	java/lang/StringBuilder:<init>	(Ljava/lang/String;)V
    //   225: aload_2
    //   226: invokeinterface 134 1 0
    //   231: invokevirtual 150	java/lang/StringBuilder:append	(Ljava/lang/Object;)Ljava/lang/StringBuilder;
    //   234: invokevirtual 94	java/lang/StringBuilder:toString	()Ljava/lang/String;
    //   237: invokestatic 99	com/baidu/frontia/base/a/a/a:b	(Ljava/lang/String;Ljava/lang/String;)V
    //   240: aload_0
    //   241: getfield 15	com/baidu/android/pushservice/util/c:a	Landroid/content/Context;
    //   244: invokestatic 155	com/baidu/android/pushservice/c/b:a	(Landroid/content/Context;)Lcom/baidu/android/pushservice/c/b;
    //   247: aload_0
    //   248: getfield 15	com/baidu/android/pushservice/util/c:a	Landroid/content/Context;
    //   251: invokevirtual 160	android/content/Context:getPackageName	()Ljava/lang/String;
    //   254: invokevirtual 163	com/baidu/android/pushservice/c/b:c	(Ljava/lang/String;)Lcom/baidu/android/pushservice/c/h;
    //   257: astore_2
    //   258: aload_2
    //   259: ifnull +94 -> 353
    //   262: aload_2
    //   263: invokevirtual 167	com/baidu/android/pushservice/c/h:a	()Ljava/lang/String;
    //   266: astore_2
    //   267: aload_0
    //   268: getfield 15	com/baidu/android/pushservice/util/c:a	Landroid/content/Context;
    //   271: invokestatic 172	com/baidu/android/pushservice/PushSettings:a	(Landroid/content/Context;)Ljava/lang/String;
    //   274: astore_3
    //   275: aload_0
    //   276: getfield 15	com/baidu/android/pushservice/util/c:a	Landroid/content/Context;
    //   279: invokestatic 175	com/baidu/frontia/base/d/c:a	(Landroid/content/Context;)Ljava/lang/String;
    //   282: astore 4
    //   284: aload_0
    //   285: getfield 19	com/baidu/android/pushservice/util/c:c	Ljava/lang/String;
    //   288: invokestatic 178	com/baidu/android/pushservice/util/a:b	(Ljava/lang/String;)Ljava/lang/String;
    //   291: astore 5
    //   293: aload_0
    //   294: getfield 17	com/baidu/android/pushservice/util/c:b	Ljava/lang/String;
    //   297: invokestatic 180	com/baidu/android/pushservice/util/a:a	(Ljava/lang/String;)Ljava/lang/String;
    //   300: astore 6
    //   302: aload_0
    //   303: getfield 19	com/baidu/android/pushservice/util/c:c	Ljava/lang/String;
    //   306: invokestatic 184	java/lang/Integer:parseInt	(Ljava/lang/String;)I
    //   309: istore_1
    //   310: aload_0
    //   311: getfield 15	com/baidu/android/pushservice/util/c:a	Landroid/content/Context;
    //   314: aload_2
    //   315: aload_3
    //   316: aload 4
    //   318: aload 6
    //   320: iload_1
    //   321: aload 5
    //   323: invokestatic 189	com/baidu/android/pushservice/util/n:a	(Landroid/content/Context;Ljava/lang/String;Ljava/lang/String;Ljava/lang/String;Ljava/lang/String;ILjava/lang/String;)V
    //   326: return
    //   327: astore_2
    //   328: ldc 81
    //   330: new 83	java/lang/StringBuilder
    //   333: dup
    //   334: ldc -65
    //   336: invokespecial 86	java/lang/StringBuilder:<init>	(Ljava/lang/String;)V
    //   339: aload_2
    //   340: invokevirtual 194	java/lang/Exception:getMessage	()Ljava/lang/String;
    //   343: invokevirtual 93	java/lang/StringBuilder:append	(Ljava/lang/String;)Ljava/lang/StringBuilder;
    //   346: invokevirtual 94	java/lang/StringBuilder:toString	()Ljava/lang/String;
    //   349: invokestatic 197	com/baidu/frontia/base/a/a/a:e	(Ljava/lang/String;Ljava/lang/String;)V
    //   352: return
    //   353: aconst_null
    //   354: astore_2
    //   355: goto -88 -> 267
    // Local variable table:
    //   start	length	slot	name	signature
    //   0	358	0	this	c
    //   309	12	1	i	int
    //   63	103	2	localObject1	Object
    //   204	2	2	localException1	Exception
    //   210	105	2	localObject2	Object
    //   327	13	2	localException2	Exception
    //   354	1	2	localObject3	Object
    //   7	309	3	localObject4	Object
    //   282	35	4	str1	String
    //   291	31	5	str2	String
    //   300	19	6	str3	String
    // Exception table:
    //   from	to	target	type
    //   64	98	204	java/lang/Exception
    //   147	203	327	java/lang/Exception
    //   214	258	327	java/lang/Exception
    //   262	267	327	java/lang/Exception
    //   267	326	327	java/lang/Exception
  }
}

/* Location:
 * Qualified Name:     com.baidu.android.pushservice.util.c
 * Java Class Version: 6 (50.0)
 * JD-Core Version:    0.7.1
 */