package com.baidu.android.pushservice.message;

import android.content.Context;

class h
  implements Runnable
{
  h(PublicMsg paramPublicMsg, Context paramContext, String paramString1, String paramString2, String paramString3) {}
  
  /* Error */
  public void run()
  {
    // Byte code:
    //   0: new 37	com/baidu/frontia/base/b/b
    //   3: dup
    //   4: aload_0
    //   5: getfield 20	com/baidu/android/pushservice/message/h:a	Landroid/content/Context;
    //   8: invokespecial 40	com/baidu/frontia/base/b/b:<init>	(Landroid/content/Context;)V
    //   11: astore_1
    //   12: new 42	org/apache/http/client/methods/HttpPost
    //   15: dup
    //   16: new 44	java/lang/StringBuilder
    //   19: dup
    //   20: invokespecial 45	java/lang/StringBuilder:<init>	()V
    //   23: invokestatic 50	com/baidu/android/pushservice/ag:e	()Ljava/lang/String;
    //   26: invokevirtual 54	java/lang/StringBuilder:append	(Ljava/lang/String;)Ljava/lang/StringBuilder;
    //   29: aload_0
    //   30: getfield 22	com/baidu/android/pushservice/message/h:b	Ljava/lang/String;
    //   33: invokevirtual 54	java/lang/StringBuilder:append	(Ljava/lang/String;)Ljava/lang/StringBuilder;
    //   36: invokevirtual 57	java/lang/StringBuilder:toString	()Ljava/lang/String;
    //   39: invokespecial 60	org/apache/http/client/methods/HttpPost:<init>	(Ljava/lang/String;)V
    //   42: astore_2
    //   43: aload_2
    //   44: ldc 62
    //   46: ldc 64
    //   48: invokevirtual 68	org/apache/http/client/methods/HttpPost:addHeader	(Ljava/lang/String;Ljava/lang/String;)V
    //   51: new 70	java/util/ArrayList
    //   54: dup
    //   55: invokespecial 71	java/util/ArrayList:<init>	()V
    //   58: astore_3
    //   59: aload_3
    //   60: invokestatic 76	com/baidu/android/pushservice/d/c:a	(Ljava/util/List;)V
    //   63: aload_3
    //   64: new 78	org/apache/http/message/BasicNameValuePair
    //   67: dup
    //   68: ldc 80
    //   70: ldc 82
    //   72: invokespecial 84	org/apache/http/message/BasicNameValuePair:<init>	(Ljava/lang/String;Ljava/lang/String;)V
    //   75: invokeinterface 90 2 0
    //   80: pop
    //   81: aload_3
    //   82: new 78	org/apache/http/message/BasicNameValuePair
    //   85: dup
    //   86: ldc 92
    //   88: aload_0
    //   89: getfield 24	com/baidu/android/pushservice/message/h:c	Ljava/lang/String;
    //   92: invokespecial 84	org/apache/http/message/BasicNameValuePair:<init>	(Ljava/lang/String;Ljava/lang/String;)V
    //   95: invokeinterface 90 2 0
    //   100: pop
    //   101: aload_3
    //   102: new 78	org/apache/http/message/BasicNameValuePair
    //   105: dup
    //   106: ldc 94
    //   108: aload_0
    //   109: getfield 26	com/baidu/android/pushservice/message/h:d	Ljava/lang/String;
    //   112: invokespecial 84	org/apache/http/message/BasicNameValuePair:<init>	(Ljava/lang/String;Ljava/lang/String;)V
    //   115: invokeinterface 90 2 0
    //   120: pop
    //   121: aload_3
    //   122: invokeinterface 98 1 0
    //   127: astore 4
    //   129: aload 4
    //   131: invokeinterface 104 1 0
    //   136: ifeq +94 -> 230
    //   139: aload 4
    //   141: invokeinterface 108 1 0
    //   146: checkcast 110	org/apache/http/NameValuePair
    //   149: astore 5
    //   151: ldc 112
    //   153: new 44	java/lang/StringBuilder
    //   156: dup
    //   157: ldc 114
    //   159: invokespecial 115	java/lang/StringBuilder:<init>	(Ljava/lang/String;)V
    //   162: aload 5
    //   164: invokevirtual 116	java/lang/Object:toString	()Ljava/lang/String;
    //   167: invokevirtual 54	java/lang/StringBuilder:append	(Ljava/lang/String;)Ljava/lang/StringBuilder;
    //   170: invokevirtual 57	java/lang/StringBuilder:toString	()Ljava/lang/String;
    //   173: invokestatic 120	com/baidu/frontia/base/a/a/a:c	(Ljava/lang/String;Ljava/lang/String;)V
    //   176: goto -47 -> 129
    //   179: astore_2
    //   180: ldc 112
    //   182: new 44	java/lang/StringBuilder
    //   185: dup
    //   186: ldc 122
    //   188: invokespecial 115	java/lang/StringBuilder:<init>	(Ljava/lang/String;)V
    //   191: aload_2
    //   192: invokevirtual 125	java/io/IOException:getMessage	()Ljava/lang/String;
    //   195: invokevirtual 54	java/lang/StringBuilder:append	(Ljava/lang/String;)Ljava/lang/StringBuilder;
    //   198: invokevirtual 57	java/lang/StringBuilder:toString	()Ljava/lang/String;
    //   201: aload_0
    //   202: getfield 20	com/baidu/android/pushservice/message/h:a	Landroid/content/Context;
    //   205: invokevirtual 131	android/content/Context:getApplicationContext	()Landroid/content/Context;
    //   208: invokestatic 136	com/baidu/frontia/base/a/a/b:b	(Ljava/lang/String;Ljava/lang/String;Landroid/content/Context;)V
    //   211: ldc 112
    //   213: ldc -118
    //   215: aload_0
    //   216: getfield 20	com/baidu/android/pushservice/message/h:a	Landroid/content/Context;
    //   219: invokevirtual 131	android/content/Context:getApplicationContext	()Landroid/content/Context;
    //   222: invokestatic 136	com/baidu/frontia/base/a/a/b:b	(Ljava/lang/String;Ljava/lang/String;Landroid/content/Context;)V
    //   225: aload_1
    //   226: invokevirtual 140	com/baidu/frontia/base/b/b:a	()V
    //   229: return
    //   230: aload_2
    //   231: new 142	org/apache/http/client/entity/UrlEncodedFormEntity
    //   234: dup
    //   235: aload_3
    //   236: ldc -112
    //   238: invokespecial 147	org/apache/http/client/entity/UrlEncodedFormEntity:<init>	(Ljava/util/List;Ljava/lang/String;)V
    //   241: invokevirtual 151	org/apache/http/client/methods/HttpPost:setEntity	(Lorg/apache/http/HttpEntity;)V
    //   244: aload_1
    //   245: aload_2
    //   246: invokevirtual 155	com/baidu/frontia/base/b/b:execute	(Lorg/apache/http/client/methods/HttpUriRequest;)Lorg/apache/http/HttpResponse;
    //   249: astore_2
    //   250: aload_2
    //   251: invokeinterface 161 1 0
    //   256: invokeinterface 167 1 0
    //   261: sipush 200
    //   264: if_icmpne +22 -> 286
    //   267: ldc 112
    //   269: ldc -87
    //   271: aload_0
    //   272: getfield 20	com/baidu/android/pushservice/message/h:a	Landroid/content/Context;
    //   275: invokevirtual 131	android/content/Context:getApplicationContext	()Landroid/content/Context;
    //   278: invokestatic 171	com/baidu/frontia/base/a/a/b:c	(Ljava/lang/String;Ljava/lang/String;Landroid/content/Context;)V
    //   281: aload_1
    //   282: invokevirtual 140	com/baidu/frontia/base/b/b:a	()V
    //   285: return
    //   286: ldc 112
    //   288: new 44	java/lang/StringBuilder
    //   291: dup
    //   292: ldc -83
    //   294: invokespecial 115	java/lang/StringBuilder:<init>	(Ljava/lang/String;)V
    //   297: aload_2
    //   298: invokeinterface 161 1 0
    //   303: invokevirtual 176	java/lang/StringBuilder:append	(Ljava/lang/Object;)Ljava/lang/StringBuilder;
    //   306: invokevirtual 57	java/lang/StringBuilder:toString	()Ljava/lang/String;
    //   309: invokestatic 178	com/baidu/frontia/base/a/a/a:e	(Ljava/lang/String;Ljava/lang/String;)V
    //   312: goto -31 -> 281
    //   315: astore_2
    //   316: ldc 112
    //   318: new 44	java/lang/StringBuilder
    //   321: dup
    //   322: ldc 122
    //   324: invokespecial 115	java/lang/StringBuilder:<init>	(Ljava/lang/String;)V
    //   327: aload_2
    //   328: invokevirtual 179	java/lang/Exception:getMessage	()Ljava/lang/String;
    //   331: invokevirtual 54	java/lang/StringBuilder:append	(Ljava/lang/String;)Ljava/lang/StringBuilder;
    //   334: invokevirtual 57	java/lang/StringBuilder:toString	()Ljava/lang/String;
    //   337: aload_0
    //   338: getfield 20	com/baidu/android/pushservice/message/h:a	Landroid/content/Context;
    //   341: invokevirtual 131	android/content/Context:getApplicationContext	()Landroid/content/Context;
    //   344: invokestatic 136	com/baidu/frontia/base/a/a/b:b	(Ljava/lang/String;Ljava/lang/String;Landroid/content/Context;)V
    //   347: aload_1
    //   348: invokevirtual 140	com/baidu/frontia/base/b/b:a	()V
    //   351: return
    //   352: astore_2
    //   353: aload_1
    //   354: invokevirtual 140	com/baidu/frontia/base/b/b:a	()V
    //   357: aload_2
    //   358: athrow
    // Local variable table:
    //   start	length	slot	name	signature
    //   0	359	0	this	h
    //   11	343	1	localb	com.baidu.frontia.base.b.b
    //   42	2	2	localHttpPost	org.apache.http.client.methods.HttpPost
    //   179	67	2	localIOException	java.io.IOException
    //   249	49	2	localHttpResponse	org.apache.http.HttpResponse
    //   315	13	2	localException	Exception
    //   352	6	2	localObject	Object
    //   58	178	3	localArrayList	java.util.ArrayList
    //   127	13	4	localIterator	java.util.Iterator
    //   149	14	5	localNameValuePair	org.apache.http.NameValuePair
    // Exception table:
    //   from	to	target	type
    //   12	129	179	java/io/IOException
    //   129	176	179	java/io/IOException
    //   230	281	179	java/io/IOException
    //   286	312	179	java/io/IOException
    //   12	129	315	java/lang/Exception
    //   129	176	315	java/lang/Exception
    //   230	281	315	java/lang/Exception
    //   286	312	315	java/lang/Exception
    //   12	129	352	finally
    //   129	176	352	finally
    //   180	225	352	finally
    //   230	281	352	finally
    //   286	312	352	finally
    //   316	347	352	finally
  }
}

/* Location:
 * Qualified Name:     com.baidu.android.pushservice.message.h
 * Java Class Version: 6 (50.0)
 * JD-Core Version:    0.7.1
 */