import android.os.IBinder;
import android.os.Parcel;
import java.util.ArrayList;
import java.util.List;

final class aie
  implements aic
{
  private IBinder a;
  
  aie(IBinder paramIBinder)
  {
    a = paramIBinder;
  }
  
  public final String a()
  {
    Parcel localParcel1 = Parcel.obtain();
    Parcel localParcel2 = Parcel.obtain();
    try
    {
      localParcel1.writeInterfaceToken("com.google.android.gms.ads.internal.formats.client.INativeAppInstallAd");
      a.transact(3, localParcel1, localParcel2, 0);
      localParcel2.readException();
      String str = localParcel2.readString();
      return str;
    }
    finally
    {
      localParcel2.recycle();
      localParcel1.recycle();
    }
  }
  
  public final IBinder asBinder()
  {
    return a;
  }
  
  public final List b()
  {
    Parcel localParcel1 = Parcel.obtain();
    Parcel localParcel2 = Parcel.obtain();
    try
    {
      localParcel1.writeInterfaceToken("com.google.android.gms.ads.internal.formats.client.INativeAppInstallAd");
      a.transact(4, localParcel1, localParcel2, 0);
      localParcel2.readException();
      ArrayList localArrayList = localParcel2.readArrayList(getClass().getClassLoader());
      return localArrayList;
    }
    finally
    {
      localParcel2.recycle();
      localParcel1.recycle();
    }
  }
  
  public final String c()
  {
    Parcel localParcel1 = Parcel.obtain();
    Parcel localParcel2 = Parcel.obtain();
    try
    {
      localParcel1.writeInterfaceToken("com.google.android.gms.ads.internal.formats.client.INativeAppInstallAd");
      a.transact(5, localParcel1, localParcel2, 0);
      localParcel2.readException();
      String str = localParcel2.readString();
      return str;
    }
    finally
    {
      localParcel2.recycle();
      localParcel1.recycle();
    }
  }
  
  public final ahs d()
  {
    Parcel localParcel1 = Parcel.obtain();
    Parcel localParcel2 = Parcel.obtain();
    try
    {
      localParcel1.writeInterfaceToken("com.google.android.gms.ads.internal.formats.client.INativeAppInstallAd");
      a.transact(6, localParcel1, localParcel2, 0);
      localParcel2.readException();
      ahs localahs = aht.a(localParcel2.readStrongBinder());
      return localahs;
    }
    finally
    {
      localParcel2.recycle();
      localParcel1.recycle();
    }
  }
  
  public final String e()
  {
    Parcel localParcel1 = Parcel.obtain();
    Parcel localParcel2 = Parcel.obtain();
    try
    {
      localParcel1.writeInterfaceToken("com.google.android.gms.ads.internal.formats.client.INativeAppInstallAd");
      a.transact(7, localParcel1, localParcel2, 0);
      localParcel2.readException();
      String str = localParcel2.readString();
      return str;
    }
    finally
    {
      localParcel2.recycle();
      localParcel1.recycle();
    }
  }
  
  public final double f()
  {
    Parcel localParcel1 = Parcel.obtain();
    Parcel localParcel2 = Parcel.obtain();
    try
    {
      localParcel1.writeInterfaceToken("com.google.android.gms.ads.internal.formats.client.INativeAppInstallAd");
      a.transact(8, localParcel1, localParcel2, 0);
      localParcel2.readException();
      double d = localParcel2.readDouble();
      return d;
    }
    finally
    {
      localParcel2.recycle();
      localParcel1.recycle();
    }
  }
  
  public final String g()
  {
    Parcel localParcel1 = Parcel.obtain();
    Parcel localParcel2 = Parcel.obtain();
    try
    {
      localParcel1.writeInterfaceToken("com.google.android.gms.ads.internal.formats.client.INativeAppInstallAd");
      a.transact(9, localParcel1, localParcel2, 0);
      localParcel2.readException();
      String str = localParcel2.readString();
      return str;
    }
    finally
    {
      localParcel2.recycle();
      localParcel1.recycle();
    }
  }
  
  public final String h()
  {
    Parcel localParcel1 = Parcel.obtain();
    Parcel localParcel2 = Parcel.obtain();
    try
    {
      localParcel1.writeInterfaceToken("com.google.android.gms.ads.internal.formats.client.INativeAppInstallAd");
      a.transact(10, localParcel1, localParcel2, 0);
      localParcel2.readException();
      String str = localParcel2.readString();
      return str;
    }
    finally
    {
      localParcel2.recycle();
      localParcel1.recycle();
    }
  }
  
  public final add i()
  {
    Parcel localParcel1 = Parcel.obtain();
    Parcel localParcel2 = Parcel.obtain();
    try
    {
      localParcel1.writeInterfaceToken("com.google.android.gms.ads.internal.formats.client.INativeAppInstallAd");
      a.transact(2, localParcel1, localParcel2, 0);
      localParcel2.readException();
      add localadd = ade.a(localParcel2.readStrongBinder());
      return localadd;
    }
    finally
    {
      localParcel2.recycle();
      localParcel1.recycle();
    }
  }
  
  /* Error */
  public final android.os.Bundle m()
  {
    // Byte code:
    //   0: invokestatic 23	android/os/Parcel:obtain	()Landroid/os/Parcel;
    //   3: astore_2
    //   4: invokestatic 23	android/os/Parcel:obtain	()Landroid/os/Parcel;
    //   7: astore_3
    //   8: aload_2
    //   9: ldc 25
    //   11: invokevirtual 29	android/os/Parcel:writeInterfaceToken	(Ljava/lang/String;)V
    //   14: aload_0
    //   15: getfield 15	aie:a	Landroid/os/IBinder;
    //   18: bipush 11
    //   20: aload_2
    //   21: aload_3
    //   22: iconst_0
    //   23: invokeinterface 35 5 0
    //   28: pop
    //   29: aload_3
    //   30: invokevirtual 38	android/os/Parcel:readException	()V
    //   33: aload_3
    //   34: invokevirtual 94	android/os/Parcel:readInt	()I
    //   37: ifeq +26 -> 63
    //   40: getstatic 100	android/os/Bundle:CREATOR	Landroid/os/Parcelable$Creator;
    //   43: aload_3
    //   44: invokeinterface 106 2 0
    //   49: checkcast 96	android/os/Bundle
    //   52: astore_1
    //   53: aload_3
    //   54: invokevirtual 44	android/os/Parcel:recycle	()V
    //   57: aload_2
    //   58: invokevirtual 44	android/os/Parcel:recycle	()V
    //   61: aload_1
    //   62: areturn
    //   63: aconst_null
    //   64: astore_1
    //   65: goto -12 -> 53
    //   68: astore_1
    //   69: aload_3
    //   70: invokevirtual 44	android/os/Parcel:recycle	()V
    //   73: aload_2
    //   74: invokevirtual 44	android/os/Parcel:recycle	()V
    //   77: aload_1
    //   78: athrow
    // Local variable table:
    //   start	length	slot	name	signature
    //   0	79	0	this	aie
    //   52	13	1	localBundle	android.os.Bundle
    //   68	10	1	localObject	Object
    //   3	71	2	localParcel1	Parcel
    //   7	63	3	localParcel2	Parcel
    // Exception table:
    //   from	to	target	type
    //   8	53	68	finally
  }
  
  public final void n()
  {
    Parcel localParcel1 = Parcel.obtain();
    Parcel localParcel2 = Parcel.obtain();
    try
    {
      localParcel1.writeInterfaceToken("com.google.android.gms.ads.internal.formats.client.INativeAppInstallAd");
      a.transact(12, localParcel1, localParcel2, 0);
      localParcel2.readException();
      return;
    }
    finally
    {
      localParcel2.recycle();
      localParcel1.recycle();
    }
  }
}

/* Location:
 * Qualified Name:     aie
 * Java Class Version: 6 (50.0)
 * JD-Core Version:    0.7.1
 */