import java.net.URL;
import java.util.Map;

final class bcj
  implements Runnable
{
  private final URL b;
  private final byte[] c;
  private final bch d;
  private final String e;
  private final Map<String, String> f;
  
  public bcj(String paramString, URL paramURL, byte[] paramArrayOfByte, Map<String, String> paramMap, bch parambch)
  {
    abe.a(paramURL);
    abe.a(paramArrayOfByte);
    Object localObject;
    abe.a(localObject);
    b = paramArrayOfByte;
    c = paramMap;
    d = ((bch)localObject);
    e = paramURL;
    f = parambch;
  }
  
  /* Error */
  public final void run()
  {
    // Byte code:
    //   0: aload_0
    //   1: getfield 23	bcj:a	Lbcg;
    //   4: invokevirtual 54	bcg:e	()V
    //   7: aload_0
    //   8: getfield 36	bcj:b	Ljava/net/URL;
    //   11: invokestatic 57	bcg:a	(Ljava/net/URL;)Ljava/net/HttpURLConnection;
    //   14: astore_2
    //   15: aload_0
    //   16: getfield 44	bcj:f	Ljava/util/Map;
    //   19: ifnull +124 -> 143
    //   22: aload_0
    //   23: getfield 44	bcj:f	Ljava/util/Map;
    //   26: invokeinterface 63 1 0
    //   31: invokeinterface 69 1 0
    //   36: astore_3
    //   37: aload_3
    //   38: invokeinterface 75 1 0
    //   43: ifeq +100 -> 143
    //   46: aload_3
    //   47: invokeinterface 79 1 0
    //   52: checkcast 81	java/util/Map$Entry
    //   55: astore 4
    //   57: aload_2
    //   58: aload 4
    //   60: invokeinterface 84 1 0
    //   65: checkcast 86	java/lang/String
    //   68: aload 4
    //   70: invokeinterface 89 1 0
    //   75: checkcast 86	java/lang/String
    //   78: invokevirtual 95	java/net/HttpURLConnection:addRequestProperty	(Ljava/lang/String;Ljava/lang/String;)V
    //   81: goto -44 -> 37
    //   84: astore 4
    //   86: iconst_0
    //   87: istore_1
    //   88: aconst_null
    //   89: astore 5
    //   91: aload_2
    //   92: astore_3
    //   93: aload 5
    //   95: astore_2
    //   96: aload_2
    //   97: ifnull +7 -> 104
    //   100: aload_2
    //   101: invokevirtual 100	java/io/OutputStream:close	()V
    //   104: aload_3
    //   105: ifnull +7 -> 112
    //   108: aload_3
    //   109: invokevirtual 103	java/net/HttpURLConnection:disconnect	()V
    //   112: aload_0
    //   113: getfield 23	bcj:a	Lbcg;
    //   116: invokevirtual 107	bcg:r	()Lbcr;
    //   119: new 109	bci
    //   122: dup
    //   123: aload_0
    //   124: getfield 42	bcj:e	Ljava/lang/String;
    //   127: aload_0
    //   128: getfield 40	bcj:d	Lbch;
    //   131: iload_1
    //   132: aload 4
    //   134: aconst_null
    //   135: iconst_0
    //   136: invokespecial 112	bci:<init>	(Ljava/lang/String;Lbch;ILjava/lang/Throwable;[BB)V
    //   139: invokevirtual 117	bcr:a	(Ljava/lang/Runnable;)V
    //   142: return
    //   143: aload_0
    //   144: getfield 38	bcj:c	[B
    //   147: ifnull +79 -> 226
    //   150: aload_0
    //   151: getfield 23	bcj:a	Lbcg;
    //   154: invokevirtual 121	bcg:o	()Lbbj;
    //   157: aload_0
    //   158: getfield 38	bcj:c	[B
    //   161: invokevirtual 126	bbj:a	([B)[B
    //   164: astore 4
    //   166: aload_0
    //   167: getfield 23	bcj:a	Lbcg;
    //   170: invokevirtual 130	bcg:s	()Lbce;
    //   173: invokevirtual 136	bce:z	()Lbcf;
    //   176: ldc -118
    //   178: aload 4
    //   180: arraylength
    //   181: invokestatic 144	java/lang/Integer:valueOf	(I)Ljava/lang/Integer;
    //   184: invokevirtual 149	bcf:a	(Ljava/lang/String;Ljava/lang/Object;)V
    //   187: aload_2
    //   188: iconst_1
    //   189: invokevirtual 153	java/net/HttpURLConnection:setDoOutput	(Z)V
    //   192: aload_2
    //   193: ldc -101
    //   195: ldc -99
    //   197: invokevirtual 95	java/net/HttpURLConnection:addRequestProperty	(Ljava/lang/String;Ljava/lang/String;)V
    //   200: aload_2
    //   201: aload 4
    //   203: arraylength
    //   204: invokevirtual 161	java/net/HttpURLConnection:setFixedLengthStreamingMode	(I)V
    //   207: aload_2
    //   208: invokevirtual 164	java/net/HttpURLConnection:connect	()V
    //   211: aload_2
    //   212: invokevirtual 168	java/net/HttpURLConnection:getOutputStream	()Ljava/io/OutputStream;
    //   215: astore_3
    //   216: aload_3
    //   217: aload 4
    //   219: invokevirtual 172	java/io/OutputStream:write	([B)V
    //   222: aload_3
    //   223: invokevirtual 100	java/io/OutputStream:close	()V
    //   226: aload_2
    //   227: invokevirtual 176	java/net/HttpURLConnection:getResponseCode	()I
    //   230: istore_1
    //   231: aload_2
    //   232: invokestatic 179	bcg:a	(Ljava/net/HttpURLConnection;)[B
    //   235: astore_3
    //   236: aload_2
    //   237: ifnull +7 -> 244
    //   240: aload_2
    //   241: invokevirtual 103	java/net/HttpURLConnection:disconnect	()V
    //   244: aload_0
    //   245: getfield 23	bcj:a	Lbcg;
    //   248: invokevirtual 107	bcg:r	()Lbcr;
    //   251: new 109	bci
    //   254: dup
    //   255: aload_0
    //   256: getfield 42	bcj:e	Ljava/lang/String;
    //   259: aload_0
    //   260: getfield 40	bcj:d	Lbch;
    //   263: iload_1
    //   264: aconst_null
    //   265: aload_3
    //   266: iconst_0
    //   267: invokespecial 112	bci:<init>	(Ljava/lang/String;Lbch;ILjava/lang/Throwable;[BB)V
    //   270: invokevirtual 117	bcr:a	(Ljava/lang/Runnable;)V
    //   273: return
    //   274: astore_2
    //   275: aload_0
    //   276: getfield 23	bcj:a	Lbcg;
    //   279: invokevirtual 130	bcg:s	()Lbce;
    //   282: invokevirtual 181	bce:b	()Lbcf;
    //   285: ldc -73
    //   287: aload_2
    //   288: invokevirtual 149	bcf:a	(Ljava/lang/String;Ljava/lang/Object;)V
    //   291: goto -187 -> 104
    //   294: astore_2
    //   295: iconst_0
    //   296: istore_1
    //   297: aconst_null
    //   298: astore 4
    //   300: aconst_null
    //   301: astore_3
    //   302: aload_3
    //   303: ifnull +7 -> 310
    //   306: aload_3
    //   307: invokevirtual 100	java/io/OutputStream:close	()V
    //   310: aload 4
    //   312: ifnull +8 -> 320
    //   315: aload 4
    //   317: invokevirtual 103	java/net/HttpURLConnection:disconnect	()V
    //   320: aload_0
    //   321: getfield 23	bcj:a	Lbcg;
    //   324: invokevirtual 107	bcg:r	()Lbcr;
    //   327: new 109	bci
    //   330: dup
    //   331: aload_0
    //   332: getfield 42	bcj:e	Ljava/lang/String;
    //   335: aload_0
    //   336: getfield 40	bcj:d	Lbch;
    //   339: iload_1
    //   340: aconst_null
    //   341: aconst_null
    //   342: iconst_0
    //   343: invokespecial 112	bci:<init>	(Ljava/lang/String;Lbch;ILjava/lang/Throwable;[BB)V
    //   346: invokevirtual 117	bcr:a	(Ljava/lang/Runnable;)V
    //   349: aload_2
    //   350: athrow
    //   351: astore_3
    //   352: aload_0
    //   353: getfield 23	bcj:a	Lbcg;
    //   356: invokevirtual 130	bcg:s	()Lbce;
    //   359: invokevirtual 181	bce:b	()Lbcf;
    //   362: ldc -73
    //   364: aload_3
    //   365: invokevirtual 149	bcf:a	(Ljava/lang/String;Ljava/lang/Object;)V
    //   368: goto -58 -> 310
    //   371: astore 5
    //   373: iconst_0
    //   374: istore_1
    //   375: aconst_null
    //   376: astore_3
    //   377: aload_2
    //   378: astore 4
    //   380: aload 5
    //   382: astore_2
    //   383: goto -81 -> 302
    //   386: astore 5
    //   388: iconst_0
    //   389: istore_1
    //   390: aload_2
    //   391: astore 4
    //   393: aload 5
    //   395: astore_2
    //   396: goto -94 -> 302
    //   399: astore 5
    //   401: aconst_null
    //   402: astore_3
    //   403: aload_2
    //   404: astore 4
    //   406: aload 5
    //   408: astore_2
    //   409: goto -107 -> 302
    //   412: astore 4
    //   414: iconst_0
    //   415: istore_1
    //   416: aconst_null
    //   417: astore_2
    //   418: aconst_null
    //   419: astore_3
    //   420: goto -324 -> 96
    //   423: astore 5
    //   425: iconst_0
    //   426: istore_1
    //   427: aload_2
    //   428: astore 4
    //   430: aload_3
    //   431: astore_2
    //   432: aload 4
    //   434: astore_3
    //   435: aload 5
    //   437: astore 4
    //   439: goto -343 -> 96
    //   442: astore 4
    //   444: aconst_null
    //   445: astore 5
    //   447: aload_2
    //   448: astore_3
    //   449: aload 5
    //   451: astore_2
    //   452: goto -356 -> 96
    // Local variable table:
    //   start	length	slot	name	signature
    //   0	455	0	this	bcj
    //   87	340	1	i	int
    //   14	227	2	localObject1	Object
    //   274	14	2	localIOException1	java.io.IOException
    //   294	84	2	localObject2	Object
    //   382	70	2	localObject3	Object
    //   36	271	3	localObject4	Object
    //   351	14	3	localIOException2	java.io.IOException
    //   376	73	3	localObject5	Object
    //   55	14	4	localEntry	java.util.Map.Entry
    //   84	49	4	localIOException3	java.io.IOException
    //   164	241	4	localObject6	Object
    //   412	1	4	localIOException4	java.io.IOException
    //   428	10	4	localObject7	Object
    //   442	1	4	localIOException5	java.io.IOException
    //   89	5	5	localObject8	Object
    //   371	10	5	localObject9	Object
    //   386	8	5	localObject10	Object
    //   399	8	5	localObject11	Object
    //   423	13	5	localIOException6	java.io.IOException
    //   445	5	5	localObject12	Object
    // Exception table:
    //   from	to	target	type
    //   15	37	84	java/io/IOException
    //   37	81	84	java/io/IOException
    //   143	216	84	java/io/IOException
    //   226	231	84	java/io/IOException
    //   100	104	274	java/io/IOException
    //   7	15	294	finally
    //   306	310	351	java/io/IOException
    //   15	37	371	finally
    //   37	81	371	finally
    //   143	216	371	finally
    //   226	231	371	finally
    //   216	226	386	finally
    //   231	236	399	finally
    //   7	15	412	java/io/IOException
    //   216	226	423	java/io/IOException
    //   231	236	442	java/io/IOException
  }
}

/* Location:
 * Qualified Name:     bcj
 * Java Class Version: 6 (50.0)
 * JD-Core Version:    0.7.1
 */