import android.os.Bundle;
import android.os.IBinder;
import android.os.Parcel;
import com.google.android.gms.maps.StreetViewPanoramaOptions;

final class bcz
  implements bcx
{
  private IBinder a;
  
  bcz(IBinder paramIBinder)
  {
    a = paramIBinder;
  }
  
  /* Error */
  public final add a(add paramadd1, add paramadd2, Bundle paramBundle)
  {
    // Byte code:
    //   0: aconst_null
    //   1: astore 4
    //   3: invokestatic 23	android/os/Parcel:obtain	()Landroid/os/Parcel;
    //   6: astore 5
    //   8: invokestatic 23	android/os/Parcel:obtain	()Landroid/os/Parcel;
    //   11: astore 6
    //   13: aload 5
    //   15: ldc 25
    //   17: invokevirtual 29	android/os/Parcel:writeInterfaceToken	(Ljava/lang/String;)V
    //   20: aload_1
    //   21: ifnull +95 -> 116
    //   24: aload_1
    //   25: invokeinterface 35 1 0
    //   30: astore_1
    //   31: aload 5
    //   33: aload_1
    //   34: invokevirtual 38	android/os/Parcel:writeStrongBinder	(Landroid/os/IBinder;)V
    //   37: aload 4
    //   39: astore_1
    //   40: aload_2
    //   41: ifnull +10 -> 51
    //   44: aload_2
    //   45: invokeinterface 35 1 0
    //   50: astore_1
    //   51: aload 5
    //   53: aload_1
    //   54: invokevirtual 38	android/os/Parcel:writeStrongBinder	(Landroid/os/IBinder;)V
    //   57: aload_3
    //   58: ifnull +63 -> 121
    //   61: aload 5
    //   63: iconst_1
    //   64: invokevirtual 42	android/os/Parcel:writeInt	(I)V
    //   67: aload_3
    //   68: aload 5
    //   70: iconst_0
    //   71: invokevirtual 48	android/os/Bundle:writeToParcel	(Landroid/os/Parcel;I)V
    //   74: aload_0
    //   75: getfield 15	bcz:a	Landroid/os/IBinder;
    //   78: iconst_4
    //   79: aload 5
    //   81: aload 6
    //   83: iconst_0
    //   84: invokeinterface 54 5 0
    //   89: pop
    //   90: aload 6
    //   92: invokevirtual 57	android/os/Parcel:readException	()V
    //   95: aload 6
    //   97: invokevirtual 60	android/os/Parcel:readStrongBinder	()Landroid/os/IBinder;
    //   100: invokestatic 65	ade:a	(Landroid/os/IBinder;)Ladd;
    //   103: astore_1
    //   104: aload 6
    //   106: invokevirtual 68	android/os/Parcel:recycle	()V
    //   109: aload 5
    //   111: invokevirtual 68	android/os/Parcel:recycle	()V
    //   114: aload_1
    //   115: areturn
    //   116: aconst_null
    //   117: astore_1
    //   118: goto -87 -> 31
    //   121: aload 5
    //   123: iconst_0
    //   124: invokevirtual 42	android/os/Parcel:writeInt	(I)V
    //   127: goto -53 -> 74
    //   130: astore_1
    //   131: aload 6
    //   133: invokevirtual 68	android/os/Parcel:recycle	()V
    //   136: aload 5
    //   138: invokevirtual 68	android/os/Parcel:recycle	()V
    //   141: aload_1
    //   142: athrow
    // Local variable table:
    //   start	length	slot	name	signature
    //   0	143	0	this	bcz
    //   0	143	1	paramadd1	add
    //   0	143	2	paramadd2	add
    //   0	143	3	paramBundle	Bundle
    //   1	37	4	localObject	Object
    //   6	131	5	localParcel1	Parcel
    //   11	121	6	localParcel2	Parcel
    // Exception table:
    //   from	to	target	type
    //   13	20	130	finally
    //   24	31	130	finally
    //   31	37	130	finally
    //   44	51	130	finally
    //   51	57	130	finally
    //   61	74	130	finally
    //   74	104	130	finally
    //   121	127	130	finally
  }
  
  public final bcu a()
  {
    Parcel localParcel1 = Parcel.obtain();
    Parcel localParcel2 = Parcel.obtain();
    try
    {
      localParcel1.writeInterfaceToken("com.google.android.gms.maps.internal.IStreetViewPanoramaFragmentDelegate");
      a.transact(1, localParcel1, localParcel2, 0);
      localParcel2.readException();
      bcu localbcu = bcv.a(localParcel2.readStrongBinder());
      return localbcu;
    }
    finally
    {
      localParcel2.recycle();
      localParcel1.recycle();
    }
  }
  
  public final void a(add paramadd, StreetViewPanoramaOptions paramStreetViewPanoramaOptions, Bundle paramBundle)
  {
    Parcel localParcel1 = Parcel.obtain();
    Parcel localParcel2 = Parcel.obtain();
    label127:
    for (;;)
    {
      try
      {
        localParcel1.writeInterfaceToken("com.google.android.gms.maps.internal.IStreetViewPanoramaFragmentDelegate");
        if (paramadd != null)
        {
          paramadd = paramadd.asBinder();
          localParcel1.writeStrongBinder(paramadd);
          if (paramStreetViewPanoramaOptions != null)
          {
            localParcel1.writeInt(1);
            paramStreetViewPanoramaOptions.writeToParcel(localParcel1, 0);
            if (paramBundle == null) {
              break label127;
            }
            localParcel1.writeInt(1);
            paramBundle.writeToParcel(localParcel1, 0);
            a.transact(2, localParcel1, localParcel2, 0);
            localParcel2.readException();
          }
        }
        else
        {
          paramadd = null;
          continue;
        }
        localParcel1.writeInt(0);
        continue;
        localParcel1.writeInt(0);
      }
      finally
      {
        localParcel2.recycle();
        localParcel1.recycle();
      }
    }
  }
  
  /* Error */
  public final void a(Bundle paramBundle)
  {
    // Byte code:
    //   0: invokestatic 23	android/os/Parcel:obtain	()Landroid/os/Parcel;
    //   3: astore_2
    //   4: invokestatic 23	android/os/Parcel:obtain	()Landroid/os/Parcel;
    //   7: astore_3
    //   8: aload_2
    //   9: ldc 25
    //   11: invokevirtual 29	android/os/Parcel:writeInterfaceToken	(Ljava/lang/String;)V
    //   14: aload_1
    //   15: ifnull +41 -> 56
    //   18: aload_2
    //   19: iconst_1
    //   20: invokevirtual 42	android/os/Parcel:writeInt	(I)V
    //   23: aload_1
    //   24: aload_2
    //   25: iconst_0
    //   26: invokevirtual 48	android/os/Bundle:writeToParcel	(Landroid/os/Parcel;I)V
    //   29: aload_0
    //   30: getfield 15	bcz:a	Landroid/os/IBinder;
    //   33: iconst_3
    //   34: aload_2
    //   35: aload_3
    //   36: iconst_0
    //   37: invokeinterface 54 5 0
    //   42: pop
    //   43: aload_3
    //   44: invokevirtual 57	android/os/Parcel:readException	()V
    //   47: aload_3
    //   48: invokevirtual 68	android/os/Parcel:recycle	()V
    //   51: aload_2
    //   52: invokevirtual 68	android/os/Parcel:recycle	()V
    //   55: return
    //   56: aload_2
    //   57: iconst_0
    //   58: invokevirtual 42	android/os/Parcel:writeInt	(I)V
    //   61: goto -32 -> 29
    //   64: astore_1
    //   65: aload_3
    //   66: invokevirtual 68	android/os/Parcel:recycle	()V
    //   69: aload_2
    //   70: invokevirtual 68	android/os/Parcel:recycle	()V
    //   73: aload_1
    //   74: athrow
    // Local variable table:
    //   start	length	slot	name	signature
    //   0	75	0	this	bcz
    //   0	75	1	paramBundle	Bundle
    //   3	67	2	localParcel1	Parcel
    //   7	59	3	localParcel2	Parcel
    // Exception table:
    //   from	to	target	type
    //   8	14	64	finally
    //   18	29	64	finally
    //   29	47	64	finally
    //   56	61	64	finally
  }
  
  /* Error */
  public final void a(bdj parambdj)
  {
    // Byte code:
    //   0: invokestatic 23	android/os/Parcel:obtain	()Landroid/os/Parcel;
    //   3: astore_2
    //   4: invokestatic 23	android/os/Parcel:obtain	()Landroid/os/Parcel;
    //   7: astore_3
    //   8: aload_2
    //   9: ldc 25
    //   11: invokevirtual 29	android/os/Parcel:writeInterfaceToken	(Ljava/lang/String;)V
    //   14: aload_1
    //   15: ifnull +43 -> 58
    //   18: aload_1
    //   19: invokeinterface 83 1 0
    //   24: astore_1
    //   25: aload_2
    //   26: aload_1
    //   27: invokevirtual 38	android/os/Parcel:writeStrongBinder	(Landroid/os/IBinder;)V
    //   30: aload_0
    //   31: getfield 15	bcz:a	Landroid/os/IBinder;
    //   34: bipush 12
    //   36: aload_2
    //   37: aload_3
    //   38: iconst_0
    //   39: invokeinterface 54 5 0
    //   44: pop
    //   45: aload_3
    //   46: invokevirtual 57	android/os/Parcel:readException	()V
    //   49: aload_3
    //   50: invokevirtual 68	android/os/Parcel:recycle	()V
    //   53: aload_2
    //   54: invokevirtual 68	android/os/Parcel:recycle	()V
    //   57: return
    //   58: aconst_null
    //   59: astore_1
    //   60: goto -35 -> 25
    //   63: astore_1
    //   64: aload_3
    //   65: invokevirtual 68	android/os/Parcel:recycle	()V
    //   68: aload_2
    //   69: invokevirtual 68	android/os/Parcel:recycle	()V
    //   72: aload_1
    //   73: athrow
    // Local variable table:
    //   start	length	slot	name	signature
    //   0	74	0	this	bcz
    //   0	74	1	parambdj	bdj
    //   3	66	2	localParcel1	Parcel
    //   7	58	3	localParcel2	Parcel
    // Exception table:
    //   from	to	target	type
    //   8	14	63	finally
    //   18	25	63	finally
    //   25	49	63	finally
  }
  
  public final IBinder asBinder()
  {
    return a;
  }
  
  public final void b()
  {
    Parcel localParcel1 = Parcel.obtain();
    Parcel localParcel2 = Parcel.obtain();
    try
    {
      localParcel1.writeInterfaceToken("com.google.android.gms.maps.internal.IStreetViewPanoramaFragmentDelegate");
      a.transact(5, localParcel1, localParcel2, 0);
      localParcel2.readException();
      return;
    }
    finally
    {
      localParcel2.recycle();
      localParcel1.recycle();
    }
  }
  
  /* Error */
  public final void b(Bundle paramBundle)
  {
    // Byte code:
    //   0: invokestatic 23	android/os/Parcel:obtain	()Landroid/os/Parcel;
    //   3: astore_2
    //   4: invokestatic 23	android/os/Parcel:obtain	()Landroid/os/Parcel;
    //   7: astore_3
    //   8: aload_2
    //   9: ldc 25
    //   11: invokevirtual 29	android/os/Parcel:writeInterfaceToken	(Ljava/lang/String;)V
    //   14: aload_1
    //   15: ifnull +54 -> 69
    //   18: aload_2
    //   19: iconst_1
    //   20: invokevirtual 42	android/os/Parcel:writeInt	(I)V
    //   23: aload_1
    //   24: aload_2
    //   25: iconst_0
    //   26: invokevirtual 48	android/os/Bundle:writeToParcel	(Landroid/os/Parcel;I)V
    //   29: aload_0
    //   30: getfield 15	bcz:a	Landroid/os/IBinder;
    //   33: bipush 10
    //   35: aload_2
    //   36: aload_3
    //   37: iconst_0
    //   38: invokeinterface 54 5 0
    //   43: pop
    //   44: aload_3
    //   45: invokevirtual 57	android/os/Parcel:readException	()V
    //   48: aload_3
    //   49: invokevirtual 88	android/os/Parcel:readInt	()I
    //   52: ifeq +8 -> 60
    //   55: aload_1
    //   56: aload_3
    //   57: invokevirtual 92	android/os/Bundle:readFromParcel	(Landroid/os/Parcel;)V
    //   60: aload_3
    //   61: invokevirtual 68	android/os/Parcel:recycle	()V
    //   64: aload_2
    //   65: invokevirtual 68	android/os/Parcel:recycle	()V
    //   68: return
    //   69: aload_2
    //   70: iconst_0
    //   71: invokevirtual 42	android/os/Parcel:writeInt	(I)V
    //   74: goto -45 -> 29
    //   77: astore_1
    //   78: aload_3
    //   79: invokevirtual 68	android/os/Parcel:recycle	()V
    //   82: aload_2
    //   83: invokevirtual 68	android/os/Parcel:recycle	()V
    //   86: aload_1
    //   87: athrow
    // Local variable table:
    //   start	length	slot	name	signature
    //   0	88	0	this	bcz
    //   0	88	1	paramBundle	Bundle
    //   3	80	2	localParcel1	Parcel
    //   7	72	3	localParcel2	Parcel
    // Exception table:
    //   from	to	target	type
    //   8	14	77	finally
    //   18	29	77	finally
    //   29	60	77	finally
    //   69	74	77	finally
  }
  
  public final void c()
  {
    Parcel localParcel1 = Parcel.obtain();
    Parcel localParcel2 = Parcel.obtain();
    try
    {
      localParcel1.writeInterfaceToken("com.google.android.gms.maps.internal.IStreetViewPanoramaFragmentDelegate");
      a.transact(6, localParcel1, localParcel2, 0);
      localParcel2.readException();
      return;
    }
    finally
    {
      localParcel2.recycle();
      localParcel1.recycle();
    }
  }
  
  public final void d()
  {
    Parcel localParcel1 = Parcel.obtain();
    Parcel localParcel2 = Parcel.obtain();
    try
    {
      localParcel1.writeInterfaceToken("com.google.android.gms.maps.internal.IStreetViewPanoramaFragmentDelegate");
      a.transact(7, localParcel1, localParcel2, 0);
      localParcel2.readException();
      return;
    }
    finally
    {
      localParcel2.recycle();
      localParcel1.recycle();
    }
  }
  
  public final void e()
  {
    Parcel localParcel1 = Parcel.obtain();
    Parcel localParcel2 = Parcel.obtain();
    try
    {
      localParcel1.writeInterfaceToken("com.google.android.gms.maps.internal.IStreetViewPanoramaFragmentDelegate");
      a.transact(8, localParcel1, localParcel2, 0);
      localParcel2.readException();
      return;
    }
    finally
    {
      localParcel2.recycle();
      localParcel1.recycle();
    }
  }
  
  public final void f()
  {
    Parcel localParcel1 = Parcel.obtain();
    Parcel localParcel2 = Parcel.obtain();
    try
    {
      localParcel1.writeInterfaceToken("com.google.android.gms.maps.internal.IStreetViewPanoramaFragmentDelegate");
      a.transact(9, localParcel1, localParcel2, 0);
      localParcel2.readException();
      return;
    }
    finally
    {
      localParcel2.recycle();
      localParcel1.recycle();
    }
  }
  
  public final boolean g()
  {
    boolean bool = false;
    Parcel localParcel1 = Parcel.obtain();
    Parcel localParcel2 = Parcel.obtain();
    try
    {
      localParcel1.writeInterfaceToken("com.google.android.gms.maps.internal.IStreetViewPanoramaFragmentDelegate");
      a.transact(11, localParcel1, localParcel2, 0);
      localParcel2.readException();
      int i = localParcel2.readInt();
      if (i != 0) {
        bool = true;
      }
      return bool;
    }
    finally
    {
      localParcel2.recycle();
      localParcel1.recycle();
    }
  }
}

/* Location:
 * Qualified Name:     bcz
 * Java Class Version: 6 (50.0)
 * JD-Core Version:    0.7.1
 */