import java.util.concurrent.BlockingQueue;
import java.util.concurrent.FutureTask;

final class bkn
  extends Thread
{
  private final Object b;
  private final BlockingQueue<FutureTask<?>> c;
  
  public bkn(String paramString, BlockingQueue<FutureTask<?>> paramBlockingQueue)
  {
    abs.a(paramBlockingQueue);
    b = new Object();
    BlockingQueue localBlockingQueue;
    c = localBlockingQueue;
    setName(paramBlockingQueue);
  }
  
  private void a(InterruptedException paramInterruptedException)
  {
    a.s().c().a(getName() + " was interrupted", paramInterruptedException);
  }
  
  public final void a()
  {
    synchronized (b)
    {
      b.notifyAll();
      return;
    }
  }
  
  /* Error */
  public final void run()
  {
    // Byte code:
    //   0: iconst_0
    //   1: istore_1
    //   2: iload_1
    //   3: ifne +27 -> 30
    //   6: aload_0
    //   7: getfield 15	bkn:a	Lbkk;
    //   10: invokestatic 79	bkk:a	(Lbkk;)Ljava/util/concurrent/Semaphore;
    //   13: invokevirtual 84	java/util/concurrent/Semaphore:acquire	()V
    //   16: iconst_1
    //   17: istore_1
    //   18: goto -16 -> 2
    //   21: astore_3
    //   22: aload_0
    //   23: aload_3
    //   24: invokespecial 86	bkn:a	(Ljava/lang/InterruptedException;)V
    //   27: goto -25 -> 2
    //   30: aload_0
    //   31: getfield 30	bkn:c	Ljava/util/concurrent/BlockingQueue;
    //   34: invokeinterface 92 1 0
    //   39: checkcast 94	java/util/concurrent/FutureTask
    //   42: astore_3
    //   43: aload_3
    //   44: ifnull +66 -> 110
    //   47: aload_3
    //   48: invokevirtual 96	java/util/concurrent/FutureTask:run	()V
    //   51: goto -21 -> 30
    //   54: astore 4
    //   56: aload_0
    //   57: getfield 15	bkn:a	Lbkk;
    //   60: invokestatic 99	bkk:c	(Lbkk;)Ljava/lang/Object;
    //   63: astore_3
    //   64: aload_3
    //   65: monitorenter
    //   66: aload_0
    //   67: getfield 15	bkn:a	Lbkk;
    //   70: invokestatic 79	bkk:a	(Lbkk;)Ljava/util/concurrent/Semaphore;
    //   73: invokevirtual 102	java/util/concurrent/Semaphore:release	()V
    //   76: aload_0
    //   77: getfield 15	bkn:a	Lbkk;
    //   80: invokestatic 99	bkk:c	(Lbkk;)Ljava/lang/Object;
    //   83: invokevirtual 73	java/lang/Object:notifyAll	()V
    //   86: aload_0
    //   87: aload_0
    //   88: getfield 15	bkn:a	Lbkk;
    //   91: invokestatic 106	bkk:d	(Lbkk;)Lbkn;
    //   94: if_acmpne +212 -> 306
    //   97: aload_0
    //   98: getfield 15	bkn:a	Lbkk;
    //   101: invokestatic 109	bkk:e	(Lbkk;)Lbkn;
    //   104: pop
    //   105: aload_3
    //   106: monitorexit
    //   107: aload 4
    //   109: athrow
    //   110: aload_0
    //   111: getfield 28	bkn:b	Ljava/lang/Object;
    //   114: astore_3
    //   115: aload_3
    //   116: monitorenter
    //   117: aload_0
    //   118: getfield 30	bkn:c	Ljava/util/concurrent/BlockingQueue;
    //   121: invokeinterface 112 1 0
    //   126: ifnonnull +25 -> 151
    //   129: aload_0
    //   130: getfield 15	bkn:a	Lbkk;
    //   133: invokestatic 115	bkk:b	(Lbkk;)Z
    //   136: istore_2
    //   137: iload_2
    //   138: ifne +13 -> 151
    //   141: aload_0
    //   142: getfield 28	bkn:b	Ljava/lang/Object;
    //   145: ldc2_w 116
    //   148: invokevirtual 121	java/lang/Object:wait	(J)V
    //   151: aload_3
    //   152: monitorexit
    //   153: aload_0
    //   154: getfield 15	bkn:a	Lbkk;
    //   157: invokestatic 99	bkk:c	(Lbkk;)Ljava/lang/Object;
    //   160: astore_3
    //   161: aload_3
    //   162: monitorenter
    //   163: aload_0
    //   164: getfield 30	bkn:c	Ljava/util/concurrent/BlockingQueue;
    //   167: invokeinterface 112 1 0
    //   172: ifnonnull +122 -> 294
    //   175: aload_3
    //   176: monitorexit
    //   177: aload_0
    //   178: getfield 15	bkn:a	Lbkk;
    //   181: invokestatic 99	bkk:c	(Lbkk;)Ljava/lang/Object;
    //   184: astore_3
    //   185: aload_3
    //   186: monitorenter
    //   187: aload_0
    //   188: getfield 15	bkn:a	Lbkk;
    //   191: invokestatic 79	bkk:a	(Lbkk;)Ljava/util/concurrent/Semaphore;
    //   194: invokevirtual 102	java/util/concurrent/Semaphore:release	()V
    //   197: aload_0
    //   198: getfield 15	bkn:a	Lbkk;
    //   201: invokestatic 99	bkk:c	(Lbkk;)Ljava/lang/Object;
    //   204: invokevirtual 73	java/lang/Object:notifyAll	()V
    //   207: aload_0
    //   208: aload_0
    //   209: getfield 15	bkn:a	Lbkk;
    //   212: invokestatic 106	bkk:d	(Lbkk;)Lbkn;
    //   215: if_acmpne +32 -> 247
    //   218: aload_0
    //   219: getfield 15	bkn:a	Lbkk;
    //   222: invokestatic 109	bkk:e	(Lbkk;)Lbkn;
    //   225: pop
    //   226: aload_3
    //   227: monitorexit
    //   228: return
    //   229: astore 4
    //   231: aload_0
    //   232: aload 4
    //   234: invokespecial 86	bkn:a	(Ljava/lang/InterruptedException;)V
    //   237: goto -86 -> 151
    //   240: astore 4
    //   242: aload_3
    //   243: monitorexit
    //   244: aload 4
    //   246: athrow
    //   247: aload_0
    //   248: aload_0
    //   249: getfield 15	bkn:a	Lbkk;
    //   252: invokestatic 124	bkk:f	(Lbkk;)Lbkn;
    //   255: if_acmpne +21 -> 276
    //   258: aload_0
    //   259: getfield 15	bkn:a	Lbkk;
    //   262: invokestatic 127	bkk:g	(Lbkk;)Lbkn;
    //   265: pop
    //   266: goto -40 -> 226
    //   269: astore 4
    //   271: aload_3
    //   272: monitorexit
    //   273: aload 4
    //   275: athrow
    //   276: aload_0
    //   277: getfield 15	bkn:a	Lbkk;
    //   280: invokevirtual 44	bkk:s	()Lbjx;
    //   283: invokevirtual 129	bjx:b	()Lbjy;
    //   286: ldc -125
    //   288: invokevirtual 133	bjy:a	(Ljava/lang/String;)V
    //   291: goto -65 -> 226
    //   294: aload_3
    //   295: monitorexit
    //   296: goto -266 -> 30
    //   299: astore 4
    //   301: aload_3
    //   302: monitorexit
    //   303: aload 4
    //   305: athrow
    //   306: aload_0
    //   307: aload_0
    //   308: getfield 15	bkn:a	Lbkk;
    //   311: invokestatic 124	bkk:f	(Lbkk;)Lbkn;
    //   314: if_acmpne +21 -> 335
    //   317: aload_0
    //   318: getfield 15	bkn:a	Lbkk;
    //   321: invokestatic 127	bkk:g	(Lbkk;)Lbkn;
    //   324: pop
    //   325: goto -220 -> 105
    //   328: astore 4
    //   330: aload_3
    //   331: monitorexit
    //   332: aload 4
    //   334: athrow
    //   335: aload_0
    //   336: getfield 15	bkn:a	Lbkk;
    //   339: invokevirtual 44	bkk:s	()Lbjx;
    //   342: invokevirtual 129	bjx:b	()Lbjy;
    //   345: ldc -125
    //   347: invokevirtual 133	bjy:a	(Ljava/lang/String;)V
    //   350: goto -245 -> 105
    // Local variable table:
    //   start	length	slot	name	signature
    //   0	353	0	this	bkn
    //   1	17	1	i	int
    //   136	2	2	bool	boolean
    //   21	3	3	localInterruptedException1	InterruptedException
    //   54	54	4	localObject2	Object
    //   229	4	4	localInterruptedException2	InterruptedException
    //   240	5	4	localObject3	Object
    //   269	5	4	localObject4	Object
    //   299	5	4	localObject5	Object
    //   328	5	4	localObject6	Object
    // Exception table:
    //   from	to	target	type
    //   6	16	21	java/lang/InterruptedException
    //   30	43	54	finally
    //   47	51	54	finally
    //   110	117	54	finally
    //   153	163	54	finally
    //   244	247	54	finally
    //   303	306	54	finally
    //   141	151	229	java/lang/InterruptedException
    //   117	137	240	finally
    //   141	151	240	finally
    //   151	153	240	finally
    //   231	237	240	finally
    //   242	244	240	finally
    //   187	226	269	finally
    //   226	228	269	finally
    //   247	266	269	finally
    //   271	273	269	finally
    //   276	291	269	finally
    //   163	177	299	finally
    //   294	296	299	finally
    //   301	303	299	finally
    //   66	105	328	finally
    //   105	107	328	finally
    //   306	325	328	finally
    //   330	332	328	finally
    //   335	350	328	finally
  }
}

/* Location:
 * Qualified Name:     bkn
 * Java Class Version: 6 (50.0)
 * JD-Core Version:    0.7.1
 */