import android.os.Handler;

public class buq
  extends buv
{
  private static final String a = buq.class.getSimpleName();
  private Handler b;
  private String c;
  private String d;
  private String e;
  private btf f;
  
  public buq(String paramString1, String paramString2, String paramString3, btf parambtf, Handler paramHandler)
  {
    b = paramHandler;
    c = paramString1;
    d = paramString2;
    e = paramString3;
    f = parambtf;
  }
  
  /* Error */
  public void run()
  {
    // Byte code:
    //   0: aload_0
    //   1: getfield 30	buq:b	Landroid/os/Handler;
    //   4: ifnonnull +4 -> 8
    //   7: return
    //   8: aconst_null
    //   9: astore_3
    //   10: aload_0
    //   11: getfield 30	buq:b	Landroid/os/Handler;
    //   14: aload_0
    //   15: getfield 30	buq:b	Landroid/os/Handler;
    //   18: bipush 20
    //   20: aload_0
    //   21: getfield 32	buq:c	Ljava/lang/String;
    //   24: invokestatic 47	android/os/Message:obtain	(Landroid/os/Handler;ILjava/lang/Object;)Landroid/os/Message;
    //   27: invokevirtual 53	android/os/Handler:sendMessage	(Landroid/os/Message;)Z
    //   30: pop
    //   31: new 55	org/apache/http/impl/client/DefaultHttpClient
    //   34: dup
    //   35: invokespecial 56	org/apache/http/impl/client/DefaultHttpClient:<init>	()V
    //   38: astore_2
    //   39: aload_2
    //   40: invokeinterface 62 1 0
    //   45: sipush 10000
    //   48: invokestatic 68	org/apache/http/params/HttpConnectionParams:setSoTimeout	(Lorg/apache/http/params/HttpParams;I)V
    //   51: aload_2
    //   52: invokeinterface 62 1 0
    //   57: sipush 10000
    //   60: invokestatic 71	org/apache/http/params/HttpConnectionParams:setConnectionTimeout	(Lorg/apache/http/params/HttpParams;I)V
    //   63: new 73	org/apache/http/client/methods/HttpGet
    //   66: dup
    //   67: aload_0
    //   68: getfield 32	buq:c	Ljava/lang/String;
    //   71: invokespecial 76	org/apache/http/client/methods/HttpGet:<init>	(Ljava/lang/String;)V
    //   74: astore_1
    //   75: aload_1
    //   76: ldc 78
    //   78: ldc 80
    //   80: iconst_4
    //   81: anewarray 82	java/lang/Object
    //   84: dup
    //   85: iconst_0
    //   86: aload_0
    //   87: getfield 38	buq:f	Lbtf;
    //   90: invokevirtual 86	btf:a	()Ljava/lang/String;
    //   93: aastore
    //   94: dup
    //   95: iconst_1
    //   96: aload_0
    //   97: getfield 38	buq:f	Lbtf;
    //   100: invokevirtual 88	btf:b	()Ljava/lang/String;
    //   103: aastore
    //   104: dup
    //   105: iconst_2
    //   106: aload_0
    //   107: getfield 36	buq:e	Ljava/lang/String;
    //   110: aastore
    //   111: dup
    //   112: iconst_3
    //   113: aload_0
    //   114: getfield 34	buq:d	Ljava/lang/String;
    //   117: aastore
    //   118: invokestatic 94	java/lang/String:format	(Ljava/lang/String;[Ljava/lang/Object;)Ljava/lang/String;
    //   121: invokevirtual 98	org/apache/http/client/methods/HttpGet:setHeader	(Ljava/lang/String;Ljava/lang/String;)V
    //   124: aload_1
    //   125: ldc 100
    //   127: ldc 102
    //   129: invokevirtual 98	org/apache/http/client/methods/HttpGet:setHeader	(Ljava/lang/String;Ljava/lang/String;)V
    //   132: ldc 80
    //   134: iconst_4
    //   135: anewarray 82	java/lang/Object
    //   138: dup
    //   139: iconst_0
    //   140: aload_0
    //   141: getfield 38	buq:f	Lbtf;
    //   144: invokevirtual 86	btf:a	()Ljava/lang/String;
    //   147: aastore
    //   148: dup
    //   149: iconst_1
    //   150: aload_0
    //   151: getfield 38	buq:f	Lbtf;
    //   154: invokevirtual 88	btf:b	()Ljava/lang/String;
    //   157: aastore
    //   158: dup
    //   159: iconst_2
    //   160: aload_0
    //   161: getfield 36	buq:e	Ljava/lang/String;
    //   164: aastore
    //   165: dup
    //   166: iconst_3
    //   167: aload_0
    //   168: getfield 34	buq:d	Ljava/lang/String;
    //   171: aastore
    //   172: invokestatic 94	java/lang/String:format	(Ljava/lang/String;[Ljava/lang/Object;)Ljava/lang/String;
    //   175: pop
    //   176: invokestatic 106	bvf:b	()V
    //   179: new 108	java/io/BufferedReader
    //   182: dup
    //   183: new 110	java/io/InputStreamReader
    //   186: dup
    //   187: aload_2
    //   188: aload_1
    //   189: invokeinterface 114 2 0
    //   194: invokeinterface 120 1 0
    //   199: invokeinterface 126 1 0
    //   204: ldc -128
    //   206: invokespecial 131	java/io/InputStreamReader:<init>	(Ljava/io/InputStream;Ljava/lang/String;)V
    //   209: invokespecial 134	java/io/BufferedReader:<init>	(Ljava/io/Reader;)V
    //   212: astore_1
    //   213: new 136	java/lang/StringBuilder
    //   216: dup
    //   217: invokespecial 137	java/lang/StringBuilder:<init>	()V
    //   220: astore_3
    //   221: aload_1
    //   222: invokevirtual 140	java/io/BufferedReader:readLine	()Ljava/lang/String;
    //   225: astore 4
    //   227: aload 4
    //   229: ifnull +59 -> 288
    //   232: aload_3
    //   233: aload 4
    //   235: invokevirtual 144	java/lang/StringBuilder:append	(Ljava/lang/String;)Ljava/lang/StringBuilder;
    //   238: pop
    //   239: goto -18 -> 221
    //   242: astore_3
    //   243: aload_0
    //   244: getfield 30	buq:b	Landroid/os/Handler;
    //   247: aload_0
    //   248: getfield 30	buq:b	Landroid/os/Handler;
    //   251: bipush 21
    //   253: aload_3
    //   254: invokestatic 47	android/os/Message:obtain	(Landroid/os/Handler;ILjava/lang/Object;)Landroid/os/Message;
    //   257: invokevirtual 53	android/os/Handler:sendMessage	(Landroid/os/Message;)Z
    //   260: pop
    //   261: aload_1
    //   262: invokestatic 149	bze:a	(Ljava/io/Closeable;)V
    //   265: aload_2
    //   266: ifnull +14 -> 280
    //   269: aload_2
    //   270: invokeinterface 153 1 0
    //   275: invokeinterface 158 1 0
    //   280: invokestatic 163	buw:a	()Lbuw;
    //   283: aload_0
    //   284: invokevirtual 166	buw:b	(Lbuv;)V
    //   287: return
    //   288: aload_0
    //   289: getfield 30	buq:b	Landroid/os/Handler;
    //   292: aload_0
    //   293: getfield 30	buq:b	Landroid/os/Handler;
    //   296: bipush 22
    //   298: aload_3
    //   299: invokevirtual 169	java/lang/StringBuilder:toString	()Ljava/lang/String;
    //   302: invokestatic 47	android/os/Message:obtain	(Landroid/os/Handler;ILjava/lang/Object;)Landroid/os/Message;
    //   305: invokevirtual 53	android/os/Handler:sendMessage	(Landroid/os/Message;)Z
    //   308: pop
    //   309: aload_1
    //   310: invokestatic 149	bze:a	(Ljava/io/Closeable;)V
    //   313: aload_2
    //   314: invokeinterface 153 1 0
    //   319: invokeinterface 158 1 0
    //   324: invokestatic 163	buw:a	()Lbuw;
    //   327: aload_0
    //   328: invokevirtual 166	buw:b	(Lbuv;)V
    //   331: return
    //   332: astore_1
    //   333: aconst_null
    //   334: astore_2
    //   335: aload_3
    //   336: invokestatic 149	bze:a	(Ljava/io/Closeable;)V
    //   339: aload_2
    //   340: ifnull +14 -> 354
    //   343: aload_2
    //   344: invokeinterface 153 1 0
    //   349: invokeinterface 158 1 0
    //   354: invokestatic 163	buw:a	()Lbuw;
    //   357: aload_0
    //   358: invokevirtual 166	buw:b	(Lbuv;)V
    //   361: aload_1
    //   362: athrow
    //   363: astore_1
    //   364: goto -29 -> 335
    //   367: astore 4
    //   369: aload_1
    //   370: astore_3
    //   371: aload 4
    //   373: astore_1
    //   374: goto -39 -> 335
    //   377: astore 4
    //   379: aload_1
    //   380: astore_3
    //   381: aload 4
    //   383: astore_1
    //   384: goto -49 -> 335
    //   387: astore_3
    //   388: aconst_null
    //   389: astore_2
    //   390: aconst_null
    //   391: astore_1
    //   392: goto -149 -> 243
    //   395: astore_3
    //   396: aconst_null
    //   397: astore_1
    //   398: goto -155 -> 243
    // Local variable table:
    //   start	length	slot	name	signature
    //   0	401	0	this	buq
    //   74	236	1	localObject1	Object
    //   332	30	1	localObject2	Object
    //   363	7	1	localObject3	Object
    //   373	25	1	localObject4	Object
    //   38	352	2	localDefaultHttpClient	org.apache.http.impl.client.DefaultHttpClient
    //   9	224	3	localStringBuilder	StringBuilder
    //   242	94	3	localException1	Exception
    //   370	11	3	localObject5	Object
    //   387	1	3	localException2	Exception
    //   395	1	3	localException3	Exception
    //   225	9	4	str	String
    //   367	5	4	localObject6	Object
    //   377	5	4	localObject7	Object
    // Exception table:
    //   from	to	target	type
    //   213	221	242	java/lang/Exception
    //   221	227	242	java/lang/Exception
    //   232	239	242	java/lang/Exception
    //   288	309	242	java/lang/Exception
    //   10	39	332	finally
    //   39	213	363	finally
    //   213	221	367	finally
    //   221	227	367	finally
    //   232	239	367	finally
    //   288	309	367	finally
    //   243	261	377	finally
    //   10	39	387	java/lang/Exception
    //   39	213	395	java/lang/Exception
  }
}

/* Location:
 * Qualified Name:     buq
 * Java Class Version: 6 (50.0)
 * JD-Core Version:    0.7.1
 */