import java.util.TimerTask;

final class cgm$3
  extends TimerTask
{
  cgm$3(cgm paramcgm) {}
  
  /* Error */
  public final void run()
  {
    // Byte code:
    //   0: iconst_0
    //   1: istore_2
    //   2: iconst_0
    //   3: istore_3
    //   4: iconst_0
    //   5: istore_1
    //   6: aload_0
    //   7: getfield 15	cgm$3:a	Lcgm;
    //   10: invokestatic 33	cgm:a	(Lcgm;)V
    //   13: aload_0
    //   14: getfield 15	cgm$3:a	Lcgm;
    //   17: invokestatic 37	cgm:f	(Lcgm;)Z
    //   20: ifeq +435 -> 455
    //   23: ldc 39
    //   25: astore 5
    //   27: aload 5
    //   29: astore 7
    //   31: aload 5
    //   33: astore 6
    //   35: new 41	java/io/File
    //   38: dup
    //   39: aload_0
    //   40: getfield 15	cgm$3:a	Lcgm;
    //   43: invokestatic 45	cgm:c	(Lcgm;)Landroid/content/Context;
    //   46: invokevirtual 51	android/content/Context:getFilesDir	()Ljava/io/File;
    //   49: aload_0
    //   50: getfield 15	cgm$3:a	Lcgm;
    //   53: invokestatic 54	cgm:b	(Lcgm;)Ljava/lang/String;
    //   56: invokespecial 57	java/io/File:<init>	(Ljava/io/File;Ljava/lang/String;)V
    //   59: invokevirtual 61	java/io/File:exists	()Z
    //   62: ifne +30 -> 92
    //   65: aload 5
    //   67: astore 7
    //   69: aload 5
    //   71: astore 6
    //   73: aload_0
    //   74: getfield 15	cgm$3:a	Lcgm;
    //   77: invokestatic 45	cgm:c	(Lcgm;)Landroid/content/Context;
    //   80: aload_0
    //   81: getfield 15	cgm$3:a	Lcgm;
    //   84: invokestatic 54	cgm:b	(Lcgm;)Ljava/lang/String;
    //   87: iconst_0
    //   88: invokevirtual 65	android/content/Context:openFileOutput	(Ljava/lang/String;I)Ljava/io/FileOutputStream;
    //   91: pop
    //   92: aload 5
    //   94: astore 7
    //   96: aload 5
    //   98: astore 6
    //   100: aload_0
    //   101: getfield 15	cgm$3:a	Lcgm;
    //   104: invokestatic 45	cgm:c	(Lcgm;)Landroid/content/Context;
    //   107: aload_0
    //   108: getfield 15	cgm$3:a	Lcgm;
    //   111: invokestatic 54	cgm:b	(Lcgm;)Ljava/lang/String;
    //   114: invokevirtual 69	android/content/Context:openFileInput	(Ljava/lang/String;)Ljava/io/FileInputStream;
    //   117: astore 8
    //   119: aload 5
    //   121: astore 7
    //   123: aload 5
    //   125: astore 6
    //   127: aload 8
    //   129: invokevirtual 75	java/io/FileInputStream:read	()I
    //   132: istore 4
    //   134: iload 4
    //   136: iconst_m1
    //   137: if_icmpeq +40 -> 177
    //   140: aload 5
    //   142: astore 7
    //   144: aload 5
    //   146: astore 6
    //   148: new 77	java/lang/StringBuilder
    //   151: dup
    //   152: invokespecial 78	java/lang/StringBuilder:<init>	()V
    //   155: aload 5
    //   157: invokevirtual 82	java/lang/StringBuilder:append	(Ljava/lang/String;)Ljava/lang/StringBuilder;
    //   160: iload 4
    //   162: i2c
    //   163: invokestatic 88	java/lang/Character:toString	(C)Ljava/lang/String;
    //   166: invokevirtual 82	java/lang/StringBuilder:append	(Ljava/lang/String;)Ljava/lang/StringBuilder;
    //   169: invokevirtual 91	java/lang/StringBuilder:toString	()Ljava/lang/String;
    //   172: astore 5
    //   174: goto -55 -> 119
    //   177: aload 5
    //   179: astore 7
    //   181: aload 5
    //   183: astore 6
    //   185: aload 8
    //   187: invokevirtual 94	java/io/FileInputStream:close	()V
    //   190: aload 5
    //   192: ldc 39
    //   194: invokevirtual 100	java/lang/String:equalsIgnoreCase	(Ljava/lang/String;)Z
    //   197: ifne +258 -> 455
    //   200: new 102	org/json/JSONArray
    //   203: dup
    //   204: aload 5
    //   206: invokespecial 105	org/json/JSONArray:<init>	(Ljava/lang/String;)V
    //   209: astore 5
    //   211: new 102	org/json/JSONArray
    //   214: dup
    //   215: invokespecial 106	org/json/JSONArray:<init>	()V
    //   218: pop
    //   219: aload_0
    //   220: getfield 15	cgm$3:a	Lcgm;
    //   223: invokestatic 110	cgm:d	(Lcgm;)Ljava/util/ArrayList;
    //   226: invokevirtual 115	java/util/ArrayList:size	()I
    //   229: ifle +51 -> 280
    //   232: iload_1
    //   233: aload_0
    //   234: getfield 15	cgm$3:a	Lcgm;
    //   237: invokestatic 110	cgm:d	(Lcgm;)Ljava/util/ArrayList;
    //   240: invokevirtual 115	java/util/ArrayList:size	()I
    //   243: if_icmpge +37 -> 280
    //   246: aload 5
    //   248: new 117	org/json/JSONObject
    //   251: dup
    //   252: aload_0
    //   253: getfield 15	cgm$3:a	Lcgm;
    //   256: invokestatic 110	cgm:d	(Lcgm;)Ljava/util/ArrayList;
    //   259: iload_1
    //   260: invokevirtual 121	java/util/ArrayList:get	(I)Ljava/lang/Object;
    //   263: checkcast 96	java/lang/String
    //   266: invokespecial 122	org/json/JSONObject:<init>	(Ljava/lang/String;)V
    //   269: invokevirtual 126	org/json/JSONArray:put	(Ljava/lang/Object;)Lorg/json/JSONArray;
    //   272: pop
    //   273: iload_1
    //   274: iconst_1
    //   275: iadd
    //   276: istore_1
    //   277: goto -45 -> 232
    //   280: aload 5
    //   282: invokevirtual 129	org/json/JSONArray:length	()I
    //   285: ifle +170 -> 455
    //   288: new 77	java/lang/StringBuilder
    //   291: dup
    //   292: ldc -125
    //   294: invokespecial 132	java/lang/StringBuilder:<init>	(Ljava/lang/String;)V
    //   297: aload 5
    //   299: invokevirtual 133	org/json/JSONArray:toString	()Ljava/lang/String;
    //   302: invokevirtual 82	java/lang/StringBuilder:append	(Ljava/lang/String;)Ljava/lang/StringBuilder;
    //   305: invokevirtual 91	java/lang/StringBuilder:toString	()Ljava/lang/String;
    //   308: astore 5
    //   310: aload 5
    //   312: invokevirtual 137	java/lang/String:getBytes	()[B
    //   315: astore 6
    //   317: new 139	java/net/URL
    //   320: dup
    //   321: aload_0
    //   322: getfield 15	cgm$3:a	Lcgm;
    //   325: invokestatic 142	cgm:g	(Lcgm;)Ljava/lang/String;
    //   328: invokespecial 143	java/net/URL:<init>	(Ljava/lang/String;)V
    //   331: invokevirtual 147	java/net/URL:openConnection	()Ljava/net/URLConnection;
    //   334: checkcast 149	java/net/HttpURLConnection
    //   337: astore 7
    //   339: aload 7
    //   341: ldc -105
    //   343: invokevirtual 154	java/net/HttpURLConnection:setRequestMethod	(Ljava/lang/String;)V
    //   346: aload 7
    //   348: ldc -100
    //   350: ldc -98
    //   352: invokevirtual 162	java/net/HttpURLConnection:setRequestProperty	(Ljava/lang/String;Ljava/lang/String;)V
    //   355: aload 7
    //   357: ldc -92
    //   359: aload 5
    //   361: invokevirtual 165	java/lang/String:length	()I
    //   364: invokestatic 169	java/lang/String:valueOf	(I)Ljava/lang/String;
    //   367: invokevirtual 162	java/net/HttpURLConnection:setRequestProperty	(Ljava/lang/String;Ljava/lang/String;)V
    //   370: aload 7
    //   372: iconst_1
    //   373: invokevirtual 173	java/net/HttpURLConnection:setDoOutput	(Z)V
    //   376: aload 7
    //   378: invokevirtual 177	java/net/HttpURLConnection:getOutputStream	()Ljava/io/OutputStream;
    //   381: aload 6
    //   383: invokevirtual 183	java/io/OutputStream:write	([B)V
    //   386: aload 7
    //   388: invokevirtual 186	java/net/HttpURLConnection:getResponseCode	()I
    //   391: istore_1
    //   392: aload 7
    //   394: invokevirtual 190	java/net/HttpURLConnection:getInputStream	()Ljava/io/InputStream;
    //   397: astore 5
    //   399: new 192	java/lang/StringBuffer
    //   402: dup
    //   403: invokespecial 193	java/lang/StringBuffer:<init>	()V
    //   406: astore 6
    //   408: sipush 1024
    //   411: newarray <illegal type>
    //   413: astore 7
    //   415: aload 5
    //   417: aload 7
    //   419: invokevirtual 198	java/io/InputStream:read	([B)I
    //   422: istore_2
    //   423: iload_2
    //   424: iconst_m1
    //   425: if_icmpeq +58 -> 483
    //   428: aload 6
    //   430: new 96	java/lang/String
    //   433: dup
    //   434: aload 7
    //   436: iconst_0
    //   437: iload_2
    //   438: invokespecial 201	java/lang/String:<init>	([BII)V
    //   441: invokevirtual 204	java/lang/StringBuffer:append	(Ljava/lang/String;)Ljava/lang/StringBuffer;
    //   444: pop
    //   445: goto -30 -> 415
    //   448: astore 5
    //   450: aload 5
    //   452: invokevirtual 207	java/net/MalformedURLException:printStackTrace	()V
    //   455: aload_0
    //   456: getfield 15	cgm$3:a	Lcgm;
    //   459: invokestatic 110	cgm:d	(Lcgm;)Ljava/util/ArrayList;
    //   462: invokevirtual 115	java/util/ArrayList:size	()I
    //   465: ifle +10 -> 475
    //   468: aload_0
    //   469: getfield 15	cgm$3:a	Lcgm;
    //   472: invokestatic 210	cgm:h	(Lcgm;)V
    //   475: aload_0
    //   476: getfield 15	cgm$3:a	Lcgm;
    //   479: invokestatic 213	cgm:e	(Lcgm;)V
    //   482: return
    //   483: iload_1
    //   484: sipush 200
    //   487: if_icmpne -32 -> 455
    //   490: new 117	org/json/JSONObject
    //   493: dup
    //   494: aload 6
    //   496: invokevirtual 214	java/lang/StringBuffer:toString	()Ljava/lang/String;
    //   499: invokespecial 122	org/json/JSONObject:<init>	(Ljava/lang/String;)V
    //   502: astore 5
    //   504: aload 5
    //   506: ldc -40
    //   508: invokevirtual 219	org/json/JSONObject:has	(Ljava/lang/String;)Z
    //   511: ifeq -56 -> 455
    //   514: aload 5
    //   516: ldc -40
    //   518: invokevirtual 223	org/json/JSONObject:getString	(Ljava/lang/String;)Ljava/lang/String;
    //   521: ldc -31
    //   523: invokevirtual 229	java/lang/String:equals	(Ljava/lang/Object;)Z
    //   526: ifne +18 -> 544
    //   529: aload 5
    //   531: ldc -40
    //   533: invokevirtual 223	org/json/JSONObject:getString	(Ljava/lang/String;)Ljava/lang/String;
    //   536: ldc -25
    //   538: invokevirtual 229	java/lang/String:equals	(Ljava/lang/Object;)Z
    //   541: ifeq -86 -> 455
    //   544: aload_0
    //   545: getfield 15	cgm$3:a	Lcgm;
    //   548: invokestatic 45	cgm:c	(Lcgm;)Landroid/content/Context;
    //   551: aload_0
    //   552: getfield 15	cgm$3:a	Lcgm;
    //   555: invokestatic 54	cgm:b	(Lcgm;)Ljava/lang/String;
    //   558: invokevirtual 234	android/content/Context:deleteFile	(Ljava/lang/String;)Z
    //   561: pop
    //   562: aload_0
    //   563: getfield 15	cgm$3:a	Lcgm;
    //   566: new 112	java/util/ArrayList
    //   569: dup
    //   570: invokespecial 235	java/util/ArrayList:<init>	()V
    //   573: invokestatic 238	cgm:a	(Lcgm;Ljava/util/ArrayList;)Ljava/util/ArrayList;
    //   576: pop
    //   577: goto -122 -> 455
    //   580: astore 5
    //   582: aload_0
    //   583: getfield 15	cgm$3:a	Lcgm;
    //   586: invokestatic 45	cgm:c	(Lcgm;)Landroid/content/Context;
    //   589: aload_0
    //   590: getfield 15	cgm$3:a	Lcgm;
    //   593: invokestatic 54	cgm:b	(Lcgm;)Ljava/lang/String;
    //   596: invokevirtual 234	android/content/Context:deleteFile	(Ljava/lang/String;)Z
    //   599: pop
    //   600: aload_0
    //   601: getfield 15	cgm$3:a	Lcgm;
    //   604: new 112	java/util/ArrayList
    //   607: dup
    //   608: invokespecial 235	java/util/ArrayList:<init>	()V
    //   611: invokestatic 238	cgm:a	(Lcgm;Ljava/util/ArrayList;)Ljava/util/ArrayList;
    //   614: pop
    //   615: aload 5
    //   617: invokevirtual 239	java/lang/Exception:printStackTrace	()V
    //   620: goto -165 -> 455
    //   623: astore 5
    //   625: aload 5
    //   627: invokevirtual 240	java/net/ProtocolException:printStackTrace	()V
    //   630: goto -175 -> 455
    //   633: astore 5
    //   635: aload 5
    //   637: invokevirtual 241	java/io/UnsupportedEncodingException:printStackTrace	()V
    //   640: goto -185 -> 455
    //   643: astore 5
    //   645: aload 5
    //   647: invokevirtual 242	java/io/IOException:printStackTrace	()V
    //   650: goto -195 -> 455
    //   653: astore 5
    //   655: aload 5
    //   657: invokevirtual 243	org/json/JSONException:printStackTrace	()V
    //   660: goto -205 -> 455
    //   663: astore 5
    //   665: aload 5
    //   667: invokevirtual 239	java/lang/Exception:printStackTrace	()V
    //   670: goto -215 -> 455
    //   673: astore 5
    //   675: aload 7
    //   677: astore 6
    //   679: aload 5
    //   681: invokevirtual 242	java/io/IOException:printStackTrace	()V
    //   684: aload 7
    //   686: ldc 39
    //   688: invokevirtual 100	java/lang/String:equalsIgnoreCase	(Ljava/lang/String;)Z
    //   691: ifne -236 -> 455
    //   694: new 102	org/json/JSONArray
    //   697: dup
    //   698: aload 7
    //   700: invokespecial 105	org/json/JSONArray:<init>	(Ljava/lang/String;)V
    //   703: astore 5
    //   705: new 102	org/json/JSONArray
    //   708: dup
    //   709: invokespecial 106	org/json/JSONArray:<init>	()V
    //   712: pop
    //   713: aload_0
    //   714: getfield 15	cgm$3:a	Lcgm;
    //   717: invokestatic 110	cgm:d	(Lcgm;)Ljava/util/ArrayList;
    //   720: invokevirtual 115	java/util/ArrayList:size	()I
    //   723: ifle +53 -> 776
    //   726: iload_2
    //   727: istore_1
    //   728: iload_1
    //   729: aload_0
    //   730: getfield 15	cgm$3:a	Lcgm;
    //   733: invokestatic 110	cgm:d	(Lcgm;)Ljava/util/ArrayList;
    //   736: invokevirtual 115	java/util/ArrayList:size	()I
    //   739: if_icmpge +37 -> 776
    //   742: aload 5
    //   744: new 117	org/json/JSONObject
    //   747: dup
    //   748: aload_0
    //   749: getfield 15	cgm$3:a	Lcgm;
    //   752: invokestatic 110	cgm:d	(Lcgm;)Ljava/util/ArrayList;
    //   755: iload_1
    //   756: invokevirtual 121	java/util/ArrayList:get	(I)Ljava/lang/Object;
    //   759: checkcast 96	java/lang/String
    //   762: invokespecial 122	org/json/JSONObject:<init>	(Ljava/lang/String;)V
    //   765: invokevirtual 126	org/json/JSONArray:put	(Ljava/lang/Object;)Lorg/json/JSONArray;
    //   768: pop
    //   769: iload_1
    //   770: iconst_1
    //   771: iadd
    //   772: istore_1
    //   773: goto -45 -> 728
    //   776: aload 5
    //   778: invokevirtual 129	org/json/JSONArray:length	()I
    //   781: ifle -326 -> 455
    //   784: new 77	java/lang/StringBuilder
    //   787: dup
    //   788: ldc -125
    //   790: invokespecial 132	java/lang/StringBuilder:<init>	(Ljava/lang/String;)V
    //   793: aload 5
    //   795: invokevirtual 133	org/json/JSONArray:toString	()Ljava/lang/String;
    //   798: invokevirtual 82	java/lang/StringBuilder:append	(Ljava/lang/String;)Ljava/lang/StringBuilder;
    //   801: invokevirtual 91	java/lang/StringBuilder:toString	()Ljava/lang/String;
    //   804: astore 5
    //   806: aload 5
    //   808: invokevirtual 137	java/lang/String:getBytes	()[B
    //   811: astore 6
    //   813: new 139	java/net/URL
    //   816: dup
    //   817: aload_0
    //   818: getfield 15	cgm$3:a	Lcgm;
    //   821: invokestatic 142	cgm:g	(Lcgm;)Ljava/lang/String;
    //   824: invokespecial 143	java/net/URL:<init>	(Ljava/lang/String;)V
    //   827: invokevirtual 147	java/net/URL:openConnection	()Ljava/net/URLConnection;
    //   830: checkcast 149	java/net/HttpURLConnection
    //   833: astore 7
    //   835: aload 7
    //   837: ldc -105
    //   839: invokevirtual 154	java/net/HttpURLConnection:setRequestMethod	(Ljava/lang/String;)V
    //   842: aload 7
    //   844: ldc -100
    //   846: ldc -98
    //   848: invokevirtual 162	java/net/HttpURLConnection:setRequestProperty	(Ljava/lang/String;Ljava/lang/String;)V
    //   851: aload 7
    //   853: ldc -92
    //   855: aload 5
    //   857: invokevirtual 165	java/lang/String:length	()I
    //   860: invokestatic 169	java/lang/String:valueOf	(I)Ljava/lang/String;
    //   863: invokevirtual 162	java/net/HttpURLConnection:setRequestProperty	(Ljava/lang/String;Ljava/lang/String;)V
    //   866: aload 7
    //   868: iconst_1
    //   869: invokevirtual 173	java/net/HttpURLConnection:setDoOutput	(Z)V
    //   872: aload 7
    //   874: invokevirtual 177	java/net/HttpURLConnection:getOutputStream	()Ljava/io/OutputStream;
    //   877: aload 6
    //   879: invokevirtual 183	java/io/OutputStream:write	([B)V
    //   882: aload 7
    //   884: invokevirtual 186	java/net/HttpURLConnection:getResponseCode	()I
    //   887: istore_1
    //   888: aload 7
    //   890: invokevirtual 190	java/net/HttpURLConnection:getInputStream	()Ljava/io/InputStream;
    //   893: astore 5
    //   895: new 192	java/lang/StringBuffer
    //   898: dup
    //   899: invokespecial 193	java/lang/StringBuffer:<init>	()V
    //   902: astore 6
    //   904: sipush 1024
    //   907: newarray <illegal type>
    //   909: astore 7
    //   911: aload 5
    //   913: aload 7
    //   915: invokevirtual 198	java/io/InputStream:read	([B)I
    //   918: istore_2
    //   919: iload_2
    //   920: iconst_m1
    //   921: if_icmpeq +33 -> 954
    //   924: aload 6
    //   926: new 96	java/lang/String
    //   929: dup
    //   930: aload 7
    //   932: iconst_0
    //   933: iload_2
    //   934: invokespecial 201	java/lang/String:<init>	([BII)V
    //   937: invokevirtual 204	java/lang/StringBuffer:append	(Ljava/lang/String;)Ljava/lang/StringBuffer;
    //   940: pop
    //   941: goto -30 -> 911
    //   944: astore 5
    //   946: aload 5
    //   948: invokevirtual 207	java/net/MalformedURLException:printStackTrace	()V
    //   951: goto -496 -> 455
    //   954: iload_1
    //   955: sipush 200
    //   958: if_icmpne -503 -> 455
    //   961: new 117	org/json/JSONObject
    //   964: dup
    //   965: aload 6
    //   967: invokevirtual 214	java/lang/StringBuffer:toString	()Ljava/lang/String;
    //   970: invokespecial 122	org/json/JSONObject:<init>	(Ljava/lang/String;)V
    //   973: astore 5
    //   975: aload 5
    //   977: ldc -40
    //   979: invokevirtual 219	org/json/JSONObject:has	(Ljava/lang/String;)Z
    //   982: ifeq -527 -> 455
    //   985: aload 5
    //   987: ldc -40
    //   989: invokevirtual 223	org/json/JSONObject:getString	(Ljava/lang/String;)Ljava/lang/String;
    //   992: ldc -31
    //   994: invokevirtual 229	java/lang/String:equals	(Ljava/lang/Object;)Z
    //   997: ifne +18 -> 1015
    //   1000: aload 5
    //   1002: ldc -40
    //   1004: invokevirtual 223	org/json/JSONObject:getString	(Ljava/lang/String;)Ljava/lang/String;
    //   1007: ldc -25
    //   1009: invokevirtual 229	java/lang/String:equals	(Ljava/lang/Object;)Z
    //   1012: ifeq -557 -> 455
    //   1015: aload_0
    //   1016: getfield 15	cgm$3:a	Lcgm;
    //   1019: invokestatic 45	cgm:c	(Lcgm;)Landroid/content/Context;
    //   1022: aload_0
    //   1023: getfield 15	cgm$3:a	Lcgm;
    //   1026: invokestatic 54	cgm:b	(Lcgm;)Ljava/lang/String;
    //   1029: invokevirtual 234	android/content/Context:deleteFile	(Ljava/lang/String;)Z
    //   1032: pop
    //   1033: aload_0
    //   1034: getfield 15	cgm$3:a	Lcgm;
    //   1037: new 112	java/util/ArrayList
    //   1040: dup
    //   1041: invokespecial 235	java/util/ArrayList:<init>	()V
    //   1044: invokestatic 238	cgm:a	(Lcgm;Ljava/util/ArrayList;)Ljava/util/ArrayList;
    //   1047: pop
    //   1048: goto -593 -> 455
    //   1051: astore 5
    //   1053: aload_0
    //   1054: getfield 15	cgm$3:a	Lcgm;
    //   1057: invokestatic 45	cgm:c	(Lcgm;)Landroid/content/Context;
    //   1060: aload_0
    //   1061: getfield 15	cgm$3:a	Lcgm;
    //   1064: invokestatic 54	cgm:b	(Lcgm;)Ljava/lang/String;
    //   1067: invokevirtual 234	android/content/Context:deleteFile	(Ljava/lang/String;)Z
    //   1070: pop
    //   1071: aload_0
    //   1072: getfield 15	cgm$3:a	Lcgm;
    //   1075: new 112	java/util/ArrayList
    //   1078: dup
    //   1079: invokespecial 235	java/util/ArrayList:<init>	()V
    //   1082: invokestatic 238	cgm:a	(Lcgm;Ljava/util/ArrayList;)Ljava/util/ArrayList;
    //   1085: pop
    //   1086: aload 5
    //   1088: invokevirtual 239	java/lang/Exception:printStackTrace	()V
    //   1091: goto -636 -> 455
    //   1094: astore 5
    //   1096: aload 5
    //   1098: invokevirtual 240	java/net/ProtocolException:printStackTrace	()V
    //   1101: goto -646 -> 455
    //   1104: astore 5
    //   1106: aload 5
    //   1108: invokevirtual 241	java/io/UnsupportedEncodingException:printStackTrace	()V
    //   1111: goto -656 -> 455
    //   1114: astore 5
    //   1116: aload 5
    //   1118: invokevirtual 242	java/io/IOException:printStackTrace	()V
    //   1121: goto -666 -> 455
    //   1124: astore 5
    //   1126: aload 5
    //   1128: invokevirtual 243	org/json/JSONException:printStackTrace	()V
    //   1131: goto -676 -> 455
    //   1134: astore 5
    //   1136: aload 5
    //   1138: invokevirtual 239	java/lang/Exception:printStackTrace	()V
    //   1141: goto -686 -> 455
    //   1144: astore 5
    //   1146: aload 6
    //   1148: ldc 39
    //   1150: invokevirtual 100	java/lang/String:equalsIgnoreCase	(Ljava/lang/String;)Z
    //   1153: ifne +260 -> 1413
    //   1156: new 102	org/json/JSONArray
    //   1159: dup
    //   1160: aload 6
    //   1162: invokespecial 105	org/json/JSONArray:<init>	(Ljava/lang/String;)V
    //   1165: astore 6
    //   1167: new 102	org/json/JSONArray
    //   1170: dup
    //   1171: invokespecial 106	org/json/JSONArray:<init>	()V
    //   1174: pop
    //   1175: aload_0
    //   1176: getfield 15	cgm$3:a	Lcgm;
    //   1179: invokestatic 110	cgm:d	(Lcgm;)Ljava/util/ArrayList;
    //   1182: invokevirtual 115	java/util/ArrayList:size	()I
    //   1185: ifle +53 -> 1238
    //   1188: iload_3
    //   1189: istore_1
    //   1190: iload_1
    //   1191: aload_0
    //   1192: getfield 15	cgm$3:a	Lcgm;
    //   1195: invokestatic 110	cgm:d	(Lcgm;)Ljava/util/ArrayList;
    //   1198: invokevirtual 115	java/util/ArrayList:size	()I
    //   1201: if_icmpge +37 -> 1238
    //   1204: aload 6
    //   1206: new 117	org/json/JSONObject
    //   1209: dup
    //   1210: aload_0
    //   1211: getfield 15	cgm$3:a	Lcgm;
    //   1214: invokestatic 110	cgm:d	(Lcgm;)Ljava/util/ArrayList;
    //   1217: iload_1
    //   1218: invokevirtual 121	java/util/ArrayList:get	(I)Ljava/lang/Object;
    //   1221: checkcast 96	java/lang/String
    //   1224: invokespecial 122	org/json/JSONObject:<init>	(Ljava/lang/String;)V
    //   1227: invokevirtual 126	org/json/JSONArray:put	(Ljava/lang/Object;)Lorg/json/JSONArray;
    //   1230: pop
    //   1231: iload_1
    //   1232: iconst_1
    //   1233: iadd
    //   1234: istore_1
    //   1235: goto -45 -> 1190
    //   1238: aload 6
    //   1240: invokevirtual 129	org/json/JSONArray:length	()I
    //   1243: ifle +170 -> 1413
    //   1246: new 77	java/lang/StringBuilder
    //   1249: dup
    //   1250: ldc -125
    //   1252: invokespecial 132	java/lang/StringBuilder:<init>	(Ljava/lang/String;)V
    //   1255: aload 6
    //   1257: invokevirtual 133	org/json/JSONArray:toString	()Ljava/lang/String;
    //   1260: invokevirtual 82	java/lang/StringBuilder:append	(Ljava/lang/String;)Ljava/lang/StringBuilder;
    //   1263: invokevirtual 91	java/lang/StringBuilder:toString	()Ljava/lang/String;
    //   1266: astore 6
    //   1268: aload 6
    //   1270: invokevirtual 137	java/lang/String:getBytes	()[B
    //   1273: astore 7
    //   1275: new 139	java/net/URL
    //   1278: dup
    //   1279: aload_0
    //   1280: getfield 15	cgm$3:a	Lcgm;
    //   1283: invokestatic 142	cgm:g	(Lcgm;)Ljava/lang/String;
    //   1286: invokespecial 143	java/net/URL:<init>	(Ljava/lang/String;)V
    //   1289: invokevirtual 147	java/net/URL:openConnection	()Ljava/net/URLConnection;
    //   1292: checkcast 149	java/net/HttpURLConnection
    //   1295: astore 8
    //   1297: aload 8
    //   1299: ldc -105
    //   1301: invokevirtual 154	java/net/HttpURLConnection:setRequestMethod	(Ljava/lang/String;)V
    //   1304: aload 8
    //   1306: ldc -100
    //   1308: ldc -98
    //   1310: invokevirtual 162	java/net/HttpURLConnection:setRequestProperty	(Ljava/lang/String;Ljava/lang/String;)V
    //   1313: aload 8
    //   1315: ldc -92
    //   1317: aload 6
    //   1319: invokevirtual 165	java/lang/String:length	()I
    //   1322: invokestatic 169	java/lang/String:valueOf	(I)Ljava/lang/String;
    //   1325: invokevirtual 162	java/net/HttpURLConnection:setRequestProperty	(Ljava/lang/String;Ljava/lang/String;)V
    //   1328: aload 8
    //   1330: iconst_1
    //   1331: invokevirtual 173	java/net/HttpURLConnection:setDoOutput	(Z)V
    //   1334: aload 8
    //   1336: invokevirtual 177	java/net/HttpURLConnection:getOutputStream	()Ljava/io/OutputStream;
    //   1339: aload 7
    //   1341: invokevirtual 183	java/io/OutputStream:write	([B)V
    //   1344: aload 8
    //   1346: invokevirtual 186	java/net/HttpURLConnection:getResponseCode	()I
    //   1349: istore_1
    //   1350: aload 8
    //   1352: invokevirtual 190	java/net/HttpURLConnection:getInputStream	()Ljava/io/InputStream;
    //   1355: astore 6
    //   1357: new 192	java/lang/StringBuffer
    //   1360: dup
    //   1361: invokespecial 193	java/lang/StringBuffer:<init>	()V
    //   1364: astore 7
    //   1366: sipush 1024
    //   1369: newarray <illegal type>
    //   1371: astore 8
    //   1373: aload 6
    //   1375: aload 8
    //   1377: invokevirtual 198	java/io/InputStream:read	([B)I
    //   1380: istore_2
    //   1381: iload_2
    //   1382: iconst_m1
    //   1383: if_icmpeq +33 -> 1416
    //   1386: aload 7
    //   1388: new 96	java/lang/String
    //   1391: dup
    //   1392: aload 8
    //   1394: iconst_0
    //   1395: iload_2
    //   1396: invokespecial 201	java/lang/String:<init>	([BII)V
    //   1399: invokevirtual 204	java/lang/StringBuffer:append	(Ljava/lang/String;)Ljava/lang/StringBuffer;
    //   1402: pop
    //   1403: goto -30 -> 1373
    //   1406: astore 6
    //   1408: aload 6
    //   1410: invokevirtual 207	java/net/MalformedURLException:printStackTrace	()V
    //   1413: aload 5
    //   1415: athrow
    //   1416: iload_1
    //   1417: sipush 200
    //   1420: if_icmpne -7 -> 1413
    //   1423: new 117	org/json/JSONObject
    //   1426: dup
    //   1427: aload 7
    //   1429: invokevirtual 214	java/lang/StringBuffer:toString	()Ljava/lang/String;
    //   1432: invokespecial 122	org/json/JSONObject:<init>	(Ljava/lang/String;)V
    //   1435: astore 6
    //   1437: aload 6
    //   1439: ldc -40
    //   1441: invokevirtual 219	org/json/JSONObject:has	(Ljava/lang/String;)Z
    //   1444: ifeq -31 -> 1413
    //   1447: aload 6
    //   1449: ldc -40
    //   1451: invokevirtual 223	org/json/JSONObject:getString	(Ljava/lang/String;)Ljava/lang/String;
    //   1454: ldc -31
    //   1456: invokevirtual 229	java/lang/String:equals	(Ljava/lang/Object;)Z
    //   1459: ifne +18 -> 1477
    //   1462: aload 6
    //   1464: ldc -40
    //   1466: invokevirtual 223	org/json/JSONObject:getString	(Ljava/lang/String;)Ljava/lang/String;
    //   1469: ldc -25
    //   1471: invokevirtual 229	java/lang/String:equals	(Ljava/lang/Object;)Z
    //   1474: ifeq -61 -> 1413
    //   1477: aload_0
    //   1478: getfield 15	cgm$3:a	Lcgm;
    //   1481: invokestatic 45	cgm:c	(Lcgm;)Landroid/content/Context;
    //   1484: aload_0
    //   1485: getfield 15	cgm$3:a	Lcgm;
    //   1488: invokestatic 54	cgm:b	(Lcgm;)Ljava/lang/String;
    //   1491: invokevirtual 234	android/content/Context:deleteFile	(Ljava/lang/String;)Z
    //   1494: pop
    //   1495: aload_0
    //   1496: getfield 15	cgm$3:a	Lcgm;
    //   1499: new 112	java/util/ArrayList
    //   1502: dup
    //   1503: invokespecial 235	java/util/ArrayList:<init>	()V
    //   1506: invokestatic 238	cgm:a	(Lcgm;Ljava/util/ArrayList;)Ljava/util/ArrayList;
    //   1509: pop
    //   1510: goto -97 -> 1413
    //   1513: astore 6
    //   1515: aload_0
    //   1516: getfield 15	cgm$3:a	Lcgm;
    //   1519: invokestatic 45	cgm:c	(Lcgm;)Landroid/content/Context;
    //   1522: aload_0
    //   1523: getfield 15	cgm$3:a	Lcgm;
    //   1526: invokestatic 54	cgm:b	(Lcgm;)Ljava/lang/String;
    //   1529: invokevirtual 234	android/content/Context:deleteFile	(Ljava/lang/String;)Z
    //   1532: pop
    //   1533: aload_0
    //   1534: getfield 15	cgm$3:a	Lcgm;
    //   1537: new 112	java/util/ArrayList
    //   1540: dup
    //   1541: invokespecial 235	java/util/ArrayList:<init>	()V
    //   1544: invokestatic 238	cgm:a	(Lcgm;Ljava/util/ArrayList;)Ljava/util/ArrayList;
    //   1547: pop
    //   1548: aload 6
    //   1550: invokevirtual 239	java/lang/Exception:printStackTrace	()V
    //   1553: goto -140 -> 1413
    //   1556: astore 6
    //   1558: aload 6
    //   1560: invokevirtual 240	java/net/ProtocolException:printStackTrace	()V
    //   1563: goto -150 -> 1413
    //   1566: astore 6
    //   1568: aload 6
    //   1570: invokevirtual 241	java/io/UnsupportedEncodingException:printStackTrace	()V
    //   1573: goto -160 -> 1413
    //   1576: astore 6
    //   1578: aload 6
    //   1580: invokevirtual 242	java/io/IOException:printStackTrace	()V
    //   1583: goto -170 -> 1413
    //   1586: astore 6
    //   1588: aload 6
    //   1590: invokevirtual 243	org/json/JSONException:printStackTrace	()V
    //   1593: goto -180 -> 1413
    //   1596: astore 6
    //   1598: aload 6
    //   1600: invokevirtual 239	java/lang/Exception:printStackTrace	()V
    //   1603: goto -190 -> 1413
    // Local variable table:
    //   start	length	slot	name	signature
    //   0	1606	0	this	3
    //   5	1416	1	i	int
    //   1	1395	2	j	int
    //   3	1186	3	k	int
    //   132	29	4	m	int
    //   25	391	5	localObject1	Object
    //   448	3	5	localMalformedURLException1	java.net.MalformedURLException
    //   502	28	5	localJSONObject1	org.json.JSONObject
    //   580	36	5	localException1	Exception
    //   623	3	5	localProtocolException1	java.net.ProtocolException
    //   633	3	5	localUnsupportedEncodingException1	java.io.UnsupportedEncodingException
    //   643	3	5	localIOException1	java.io.IOException
    //   653	3	5	localJSONException1	org.json.JSONException
    //   663	3	5	localException2	Exception
    //   673	7	5	localIOException2	java.io.IOException
    //   703	209	5	localObject2	Object
    //   944	3	5	localMalformedURLException2	java.net.MalformedURLException
    //   973	28	5	localJSONObject2	org.json.JSONObject
    //   1051	36	5	localException3	Exception
    //   1094	3	5	localProtocolException2	java.net.ProtocolException
    //   1104	3	5	localUnsupportedEncodingException2	java.io.UnsupportedEncodingException
    //   1114	3	5	localIOException3	java.io.IOException
    //   1124	3	5	localJSONException2	org.json.JSONException
    //   1134	3	5	localException4	Exception
    //   1144	270	5	localObject3	Object
    //   33	1341	6	localObject4	Object
    //   1406	3	6	localMalformedURLException3	java.net.MalformedURLException
    //   1435	28	6	localJSONObject3	org.json.JSONObject
    //   1513	36	6	localException5	Exception
    //   1556	3	6	localProtocolException3	java.net.ProtocolException
    //   1566	3	6	localUnsupportedEncodingException3	java.io.UnsupportedEncodingException
    //   1576	3	6	localIOException4	java.io.IOException
    //   1586	3	6	localJSONException3	org.json.JSONException
    //   1596	3	6	localException6	Exception
    //   29	1399	7	localObject5	Object
    //   117	1276	8	localObject6	Object
    // Exception table:
    //   from	to	target	type
    //   190	232	448	java/net/MalformedURLException
    //   232	273	448	java/net/MalformedURLException
    //   280	415	448	java/net/MalformedURLException
    //   415	423	448	java/net/MalformedURLException
    //   428	445	448	java/net/MalformedURLException
    //   490	544	448	java/net/MalformedURLException
    //   544	577	448	java/net/MalformedURLException
    //   582	620	448	java/net/MalformedURLException
    //   490	544	580	java/lang/Exception
    //   544	577	580	java/lang/Exception
    //   190	232	623	java/net/ProtocolException
    //   232	273	623	java/net/ProtocolException
    //   280	415	623	java/net/ProtocolException
    //   415	423	623	java/net/ProtocolException
    //   428	445	623	java/net/ProtocolException
    //   490	544	623	java/net/ProtocolException
    //   544	577	623	java/net/ProtocolException
    //   582	620	623	java/net/ProtocolException
    //   190	232	633	java/io/UnsupportedEncodingException
    //   232	273	633	java/io/UnsupportedEncodingException
    //   280	415	633	java/io/UnsupportedEncodingException
    //   415	423	633	java/io/UnsupportedEncodingException
    //   428	445	633	java/io/UnsupportedEncodingException
    //   490	544	633	java/io/UnsupportedEncodingException
    //   544	577	633	java/io/UnsupportedEncodingException
    //   582	620	633	java/io/UnsupportedEncodingException
    //   190	232	643	java/io/IOException
    //   232	273	643	java/io/IOException
    //   280	415	643	java/io/IOException
    //   415	423	643	java/io/IOException
    //   428	445	643	java/io/IOException
    //   490	544	643	java/io/IOException
    //   544	577	643	java/io/IOException
    //   582	620	643	java/io/IOException
    //   190	232	653	org/json/JSONException
    //   232	273	653	org/json/JSONException
    //   280	415	653	org/json/JSONException
    //   415	423	653	org/json/JSONException
    //   428	445	653	org/json/JSONException
    //   490	544	653	org/json/JSONException
    //   544	577	653	org/json/JSONException
    //   582	620	653	org/json/JSONException
    //   190	232	663	java/lang/Exception
    //   232	273	663	java/lang/Exception
    //   280	415	663	java/lang/Exception
    //   415	423	663	java/lang/Exception
    //   428	445	663	java/lang/Exception
    //   582	620	663	java/lang/Exception
    //   35	65	673	java/io/IOException
    //   73	92	673	java/io/IOException
    //   100	119	673	java/io/IOException
    //   127	134	673	java/io/IOException
    //   148	174	673	java/io/IOException
    //   185	190	673	java/io/IOException
    //   684	726	944	java/net/MalformedURLException
    //   728	769	944	java/net/MalformedURLException
    //   776	911	944	java/net/MalformedURLException
    //   911	919	944	java/net/MalformedURLException
    //   924	941	944	java/net/MalformedURLException
    //   961	1015	944	java/net/MalformedURLException
    //   1015	1048	944	java/net/MalformedURLException
    //   1053	1091	944	java/net/MalformedURLException
    //   961	1015	1051	java/lang/Exception
    //   1015	1048	1051	java/lang/Exception
    //   684	726	1094	java/net/ProtocolException
    //   728	769	1094	java/net/ProtocolException
    //   776	911	1094	java/net/ProtocolException
    //   911	919	1094	java/net/ProtocolException
    //   924	941	1094	java/net/ProtocolException
    //   961	1015	1094	java/net/ProtocolException
    //   1015	1048	1094	java/net/ProtocolException
    //   1053	1091	1094	java/net/ProtocolException
    //   684	726	1104	java/io/UnsupportedEncodingException
    //   728	769	1104	java/io/UnsupportedEncodingException
    //   776	911	1104	java/io/UnsupportedEncodingException
    //   911	919	1104	java/io/UnsupportedEncodingException
    //   924	941	1104	java/io/UnsupportedEncodingException
    //   961	1015	1104	java/io/UnsupportedEncodingException
    //   1015	1048	1104	java/io/UnsupportedEncodingException
    //   1053	1091	1104	java/io/UnsupportedEncodingException
    //   684	726	1114	java/io/IOException
    //   728	769	1114	java/io/IOException
    //   776	911	1114	java/io/IOException
    //   911	919	1114	java/io/IOException
    //   924	941	1114	java/io/IOException
    //   961	1015	1114	java/io/IOException
    //   1015	1048	1114	java/io/IOException
    //   1053	1091	1114	java/io/IOException
    //   684	726	1124	org/json/JSONException
    //   728	769	1124	org/json/JSONException
    //   776	911	1124	org/json/JSONException
    //   911	919	1124	org/json/JSONException
    //   924	941	1124	org/json/JSONException
    //   961	1015	1124	org/json/JSONException
    //   1015	1048	1124	org/json/JSONException
    //   1053	1091	1124	org/json/JSONException
    //   684	726	1134	java/lang/Exception
    //   728	769	1134	java/lang/Exception
    //   776	911	1134	java/lang/Exception
    //   911	919	1134	java/lang/Exception
    //   924	941	1134	java/lang/Exception
    //   1053	1091	1134	java/lang/Exception
    //   35	65	1144	finally
    //   73	92	1144	finally
    //   100	119	1144	finally
    //   127	134	1144	finally
    //   148	174	1144	finally
    //   185	190	1144	finally
    //   679	684	1144	finally
    //   1146	1188	1406	java/net/MalformedURLException
    //   1190	1231	1406	java/net/MalformedURLException
    //   1238	1373	1406	java/net/MalformedURLException
    //   1373	1381	1406	java/net/MalformedURLException
    //   1386	1403	1406	java/net/MalformedURLException
    //   1423	1477	1406	java/net/MalformedURLException
    //   1477	1510	1406	java/net/MalformedURLException
    //   1515	1553	1406	java/net/MalformedURLException
    //   1423	1477	1513	java/lang/Exception
    //   1477	1510	1513	java/lang/Exception
    //   1146	1188	1556	java/net/ProtocolException
    //   1190	1231	1556	java/net/ProtocolException
    //   1238	1373	1556	java/net/ProtocolException
    //   1373	1381	1556	java/net/ProtocolException
    //   1386	1403	1556	java/net/ProtocolException
    //   1423	1477	1556	java/net/ProtocolException
    //   1477	1510	1556	java/net/ProtocolException
    //   1515	1553	1556	java/net/ProtocolException
    //   1146	1188	1566	java/io/UnsupportedEncodingException
    //   1190	1231	1566	java/io/UnsupportedEncodingException
    //   1238	1373	1566	java/io/UnsupportedEncodingException
    //   1373	1381	1566	java/io/UnsupportedEncodingException
    //   1386	1403	1566	java/io/UnsupportedEncodingException
    //   1423	1477	1566	java/io/UnsupportedEncodingException
    //   1477	1510	1566	java/io/UnsupportedEncodingException
    //   1515	1553	1566	java/io/UnsupportedEncodingException
    //   1146	1188	1576	java/io/IOException
    //   1190	1231	1576	java/io/IOException
    //   1238	1373	1576	java/io/IOException
    //   1373	1381	1576	java/io/IOException
    //   1386	1403	1576	java/io/IOException
    //   1423	1477	1576	java/io/IOException
    //   1477	1510	1576	java/io/IOException
    //   1515	1553	1576	java/io/IOException
    //   1146	1188	1586	org/json/JSONException
    //   1190	1231	1586	org/json/JSONException
    //   1238	1373	1586	org/json/JSONException
    //   1373	1381	1586	org/json/JSONException
    //   1386	1403	1586	org/json/JSONException
    //   1423	1477	1586	org/json/JSONException
    //   1477	1510	1586	org/json/JSONException
    //   1515	1553	1586	org/json/JSONException
    //   1146	1188	1596	java/lang/Exception
    //   1190	1231	1596	java/lang/Exception
    //   1238	1373	1596	java/lang/Exception
    //   1373	1381	1596	java/lang/Exception
    //   1386	1403	1596	java/lang/Exception
    //   1515	1553	1596	java/lang/Exception
  }
}

/* Location:
 * Qualified Name:     cgm.3
 * Java Class Version: 6 (50.0)
 * JD-Core Version:    0.7.1
 */