public final class cmy
  implements cmu
{
  private cna a;
  private cnj b;
  private boolean c;
  
  private cmy(cna paramcna1, cna paramcna2, cmx<cnh> paramcmx, cnk paramcnk, cnw paramcnw, cof paramcof)
  {
    a = paramcna1;
    b = cnj.a(paramcna1, paramcna2, paramcmx, paramcnk, paramcnw, paramcof);
  }
  
  private boolean d()
  {
    try
    {
      boolean bool = c;
      return bool;
    }
    finally
    {
      localObject = finally;
      throw ((Throwable)localObject);
    }
  }
  
  /* Error */
  public final void a()
  {
    // Byte code:
    //   0: aload_0
    //   1: monitorenter
    //   2: aload_0
    //   3: invokespecial 38	cmy:d	()Z
    //   6: istore_1
    //   7: iload_1
    //   8: ifeq +6 -> 14
    //   11: aload_0
    //   12: monitorexit
    //   13: return
    //   14: aload_0
    //   15: iconst_1
    //   16: putfield 36	cmy:c	Z
    //   19: aload_0
    //   20: getfield 26	cmy:b	Lcnj;
    //   23: invokevirtual 40	cnj:a	()V
    //   26: goto -15 -> 11
    //   29: astore_2
    //   30: aload_0
    //   31: monitorexit
    //   32: aload_2
    //   33: athrow
    // Local variable table:
    //   start	length	slot	name	signature
    //   0	34	0	this	cmy
    //   6	2	1	bool	boolean
    //   29	4	2	localObject	Object
    // Exception table:
    //   from	to	target	type
    //   2	7	29	finally
    //   14	26	29	finally
  }
  
  /* Error */
  public final void b()
  {
    // Byte code:
    //   0: aload_0
    //   1: monitorenter
    //   2: aload_0
    //   3: invokespecial 38	cmy:d	()Z
    //   6: istore_1
    //   7: iload_1
    //   8: ifne +6 -> 14
    //   11: aload_0
    //   12: monitorexit
    //   13: return
    //   14: aload_0
    //   15: iconst_0
    //   16: putfield 36	cmy:c	Z
    //   19: aload_0
    //   20: getfield 26	cmy:b	Lcnj;
    //   23: invokevirtual 42	cnj:b	()V
    //   26: goto -15 -> 11
    //   29: astore_2
    //   30: aload_0
    //   31: monitorexit
    //   32: aload_2
    //   33: athrow
    // Local variable table:
    //   start	length	slot	name	signature
    //   0	34	0	this	cmy
    //   6	2	1	bool	boolean
    //   29	4	2	localObject	Object
    // Exception table:
    //   from	to	target	type
    //   2	7	29	finally
    //   14	26	29	finally
  }
  
  public final cnd c()
  {
    return a;
  }
}

/* Location:
 * Qualified Name:     cmy
 * Java Class Version: 6 (50.0)
 * JD-Core Version:    0.7.1
 */